{
    "id": "WAM_XMLExport_AAC_Objects.xml",
    "name": "WAM_XMLExport_AAC_Objects.xml",
    "description": null,
    "sourceColumns": [
        {
            "id": "HN47535",
            "hNodeId": "HN47535",
            "columnName": "ObjectID"
        },
        {
            "id": "HN47555",
            "hNodeId": "HN47555",
            "columnName": "Term"
        },
        {
            "id": "HN85473",
            "hNodeId": "HN85473",
            "columnName": "MediumTermURI"
        },
        {
            "id": "HN91637",
            "hNodeId": "HN91637",
            "columnName": "ObjectIdURI"
        },
        {
            "id": "HN84669",
            "hNodeId": "HN84669",
            "columnName": "MediumURI"
        },
        {
            "id": "HN47537",
            "hNodeId": "HN47537",
            "columnName": "ObjectNumber"
        },
        {
            "id": "HN92441",
            "hNodeId": "HN92441",
            "columnName": "ObjectIdLabel"
        },
        {
            "id": "HN47517",
            "hNodeId": "HN47517",
            "columnName": "Classification"
        },
        {
            "id": "HN47571",
            "hNodeId": "HN47571",
            "columnName": "ResourceURL"
        },
        {
            "id": "HN93245",
            "hNodeId": "HN93245",
            "columnName": "ObjectNoURI"
        },
        {
            "id": "HN81451",
            "hNodeId": "HN81451",
            "columnName": "ClassificationEventURI"
        },
        {
            "id": "HN82255",
            "hNodeId": "HN82255",
            "columnName": "CreditLineURI"
        },
        {
            "id": "HN47519",
            "hNodeId": "HN47519",
            "columnName": "CreditLine"
        },
        {
            "id": "HN83061",
            "hNodeId": "HN83061",
            "columnName": "ProductionURI"
        },
        {
            "id": "HN89223",
            "hNodeId": "HN89223",
            "columnName": "DescriptionURI"
        },
        {
            "id": "HN79843",
            "hNodeId": "HN79843",
            "columnName": "ObjectURI"
        },
        {
            "id": "HN87348",
            "hNodeId": "HN87348",
            "columnName": "MediumLodTerm"
        },
        {
            "id": "HN47525",
            "hNodeId": "HN47525",
            "columnName": "DateBegin"
        },
        {
            "id": "HN47544",
            "hNodeId": "HN47544",
            "columnName": "Medium"
        },
        {
            "id": "HN94050",
            "hNodeId": "HN94050",
            "columnName": "OwnerLabel"
        },
        {
            "id": "HN47569",
            "hNodeId": "HN47569",
            "columnName": "PublicDescription"
        },
        {
            "id": "HN80647",
            "hNodeId": "HN80647",
            "columnName": "ClassificationURI"
        },
        {
            "id": "HN90027",
            "hNodeId": "HN90027",
            "columnName": "UrlURI"
        },
        {
            "id": "HN47527",
            "hNodeId": "HN47527",
            "columnName": "DateEnd"
        },
        {
            "id": "HN47529",
            "hNodeId": "HN47529",
            "columnName": "Dated"
        },
        {
            "id": "HN83865",
            "hNodeId": "HN83865",
            "columnName": "ProductionTimespanURI"
        },
        {
            "id": "HN90833",
            "hNodeId": "HN90833",
            "columnName": "CurrentOwnerURI"
        }
    ],
    "mappingToSourceColumns": [
        {
            "id": "HN47535",
            "sourceColumnId": "HN47535"
        },
        {
            "id": "HN47555",
            "sourceColumnId": "HN47555"
        },
        {
            "id": "HN91637",
            "sourceColumnId": "HN91637"
        },
        {
            "id": "HN85473",
            "sourceColumnId": "HN85473"
        },
        {
            "id": "HN84669",
            "sourceColumnId": "HN84669"
        },
        {
            "id": "HN47537",
            "sourceColumnId": "HN47537"
        },
        {
            "id": "HN92441",
            "sourceColumnId": "HN92441"
        },
        {
            "id": "HN47517",
            "sourceColumnId": "HN47517"
        },
        {
            "id": "HN93245",
            "sourceColumnId": "HN93245"
        },
        {
            "id": "HN47571",
            "sourceColumnId": "HN47571"
        },
        {
            "id": "HN81451",
            "sourceColumnId": "HN81451"
        },
        {
            "id": "HN82255",
            "sourceColumnId": "HN82255"
        },
        {
            "id": "HN47519",
            "sourceColumnId": "HN47519"
        },
        {
            "id": "HN83061",
            "sourceColumnId": "HN83061"
        },
        {
            "id": "HN89223",
            "sourceColumnId": "HN89223"
        },
        {
            "id": "HN79843",
            "sourceColumnId": "HN79843"
        },
        {
            "id": "HN87348",
            "sourceColumnId": "HN87348"
        },
        {
            "id": "HN47525",
            "sourceColumnId": "HN47525"
        },
        {
            "id": "HN47544",
            "sourceColumnId": "HN47544"
        },
        {
            "id": "HN94050",
            "sourceColumnId": "HN94050"
        },
        {
            "id": "HN47569",
            "sourceColumnId": "HN47569"
        },
        {
            "id": "HN80647",
            "sourceColumnId": "HN80647"
        },
        {
            "id": "HN90027",
            "sourceColumnId": "HN90027"
        },
        {
            "id": "HN47527",
            "sourceColumnId": "HN47527"
        },
        {
            "id": "HN47529",
            "sourceColumnId": "HN47529"
        },
        {
            "id": "HN83865",
            "sourceColumnId": "HN83865"
        },
        {
            "id": "HN90833",
            "sourceColumnId": "HN90833"
        }
    ],
    "graph": {
        "nodes": [
            {
                "id": "http://www.cidoc-crm.org/cidoc-crm/E12_Production1",
                "label": {
                    "uri": "http://www.cidoc-crm.org/cidoc-crm/E12_Production",
                    "rdfsLabel": null
                },
                "type": "InternalNode",
                "modelIds": null
            },
            {
                "id": "http://www.cidoc-crm.org/cidoc-crm/E52_Time-Span1",
                "label": {
                    "uri": "http://www.cidoc-crm.org/cidoc-crm/E52_Time-Span",
                    "rdfsLabel": null
                },
                "type": "InternalNode",
                "modelIds": null
            },
            {
                "id": "http://www.cidoc-crm.org/cidoc-crm/E17_Type_Assignment1",
                "label": {
                    "uri": "http://www.cidoc-crm.org/cidoc-crm/E17_Type_Assignment",
                    "rdfsLabel": null
                },
                "type": "InternalNode",
                "modelIds": null
            },
            {
                "id": "http://www.cidoc-crm.org/cidoc-crm/E55_Type1",
                "label": {
                    "uri": "http://www.cidoc-crm.org/cidoc-crm/E55_Type",
                    "rdfsLabel": null
                },
                "type": "InternalNode",
                "modelIds": null
            },
            {
                "id": "http://www.cidoc-crm.org/cidoc-crm/E22_Man-Made_Object1",
                "label": {
                    "uri": "http://www.cidoc-crm.org/cidoc-crm/E22_Man-Made_Object",
                    "rdfsLabel": null
                },
                "type": "InternalNode",
                "modelIds": null
            },
            {
                "id": "http://www.cidoc-crm.org/cidoc-crm/E33_Linguistic_Object1",
                "label": {
                    "uri": "http://www.cidoc-crm.org/cidoc-crm/E33_Linguistic_Object",
                    "rdfsLabel": null
                },
                "type": "InternalNode",
                "modelIds": null
            },
            {
                "id": "http://www.cidoc-crm.org/cidoc-crm/E33_Linguistic_Object2",
                "label": {
                    "uri": "http://www.cidoc-crm.org/cidoc-crm/E33_Linguistic_Object",
                    "rdfsLabel": null
                },
                "type": "InternalNode",
                "modelIds": null
            },
            {
                "id": "http://www.cidoc-crm.org/cidoc-crm/E33_Linguistic_Object3",
                "label": {
                    "uri": "http://www.cidoc-crm.org/cidoc-crm/E33_Linguistic_Object",
                    "rdfsLabel": null
                },
                "type": "InternalNode",
                "modelIds": null
            },
            {
                "id": "http://www.cidoc-crm.org/cidoc-crm/E40_Legal_Body1",
                "label": {
                    "uri": "http://www.cidoc-crm.org/cidoc-crm/E40_Legal_Body",
                    "rdfsLabel": null
                },
                "type": "InternalNode",
                "modelIds": null
            },
            {
                "id": "http://www.cidoc-crm.org/cidoc-crm/E42_Identifier1",
                "label": {
                    "uri": "http://www.cidoc-crm.org/cidoc-crm/E42_Identifier",
                    "rdfsLabel": null
                },
                "type": "InternalNode",
                "modelIds": null
            },
            {
                "id": "http://www.cidoc-crm.org/cidoc-crm/E42_Identifier2",
                "label": {
                    "uri": "http://www.cidoc-crm.org/cidoc-crm/E42_Identifier",
                    "rdfsLabel": null
                },
                "type": "InternalNode",
                "modelIds": null
            },
            {
                "id": "http://www.cidoc-crm.org/cidoc-crm/E57_Material1",
                "label": {
                    "uri": "http://www.cidoc-crm.org/cidoc-crm/E57_Material",
                    "rdfsLabel": null
                },
                "type": "InternalNode",
                "modelIds": null
            },
            {
                "id": "http://xmlns.com/foaf/0.1/Document1",
                "label": {
                    "uri": "http://xmlns.com/foaf/0.1/Document",
                    "rdfsLabel": null
                },
                "type": "InternalNode",
                "modelIds": null
            },
            {
                "id": "HN47535",
                "label": {
                    "uri": "HN47535",
                    "rdfsLabel": null
                },
                "type": "ColumnNode",
                "hNodeId": "HN47535",
                "columnName": "ObjectID",
                "rdfLiteralType": null,
                "language": "",
                "userSemanticTypes": [
                    {
                        "hNodeId": "HN47535",
                        "domain": {
                            "uri": "http://www.cidoc-crm.org/cidoc-crm/E42_Identifier",
                            "rdfsLabel": null
                        },
                        "type": {
                            "uri": "http://www.w3.org/1999/02/22-rdf-syntax-ns#value",
                            "rdfsLabel": null
                        },
                        "origin": "User",
                        "confidenceScore": 1.0
                    },
                    {
                        "hNodeId": "HN47535",
                        "domain": {
                            "uri": "http://www.cidoc-crm.org/cidoc-crm/E42_Identifier",
                            "rdfsLabel": null
                        },
                        "type": {
                            "uri": "http://www.w3.org/1999/02/22-rdf-syntax-ns#value",
                            "rdfsLabel": null
                        },
                        "origin": "User",
                        "confidenceScore": 1.0
                    }
                ],
                "learnedSemanticTypes": null,
                "modelIds": null
            },
            {
                "id": "HN47555",
                "label": {
                    "uri": "HN47555",
                    "rdfsLabel": null
                },
                "type": "ColumnNode",
                "hNodeId": "HN47555",
                "columnName": "Term",
                "rdfLiteralType": null,
                "language": "",
                "userSemanticTypes": [
                    {
                        "hNodeId": "HN47555",
                        "domain": {
                            "uri": "http://www.cidoc-crm.org/cidoc-crm/E57_Material",
                            "rdfsLabel": null
                        },
                        "type": {
                            "uri": "http://www.w3.org/2004/02/skos/core#prefLabel",
                            "rdfsLabel": "preferred label"
                        },
                        "origin": "User",
                        "confidenceScore": 1.0
                    },
                    {
                        "hNodeId": "HN47555",
                        "domain": {
                            "uri": "http://www.cidoc-crm.org/cidoc-crm/E57_Material",
                            "rdfsLabel": null
                        },
                        "type": {
                            "uri": "http://www.w3.org/2004/02/skos/core#prefLabel",
                            "rdfsLabel": "preferred label"
                        },
                        "origin": "User",
                        "confidenceScore": 1.0
                    }
                ],
                "learnedSemanticTypes": null,
                "modelIds": null
            },
            {
                "id": "HN85473",
                "label": {
                    "uri": "HN85473",
                    "rdfsLabel": null
                },
                "type": "ColumnNode",
                "hNodeId": "HN85473",
                "columnName": "MediumTermURI",
                "rdfLiteralType": null,
                "language": "",
                "userSemanticTypes": [
                    {
                        "hNodeId": "HN85473",
                        "domain": {
                            "uri": "http://www.cidoc-crm.org/cidoc-crm/E57_Material",
                            "rdfsLabel": null
                        },
                        "type": {
                            "uri": "http://isi.edu/integration/karma/dev#classLink",
                            "rdfsLabel": null
                        },
                        "origin": "User",
                        "confidenceScore": 1.0
                    },
                    {
                        "hNodeId": "HN85473",
                        "domain": {
                            "uri": "http://www.cidoc-crm.org/cidoc-crm/E57_Material",
                            "rdfsLabel": null
                        },
                        "type": {
                            "uri": "http://isi.edu/integration/karma/dev#classLink",
                            "rdfsLabel": null
                        },
                        "origin": "User",
                        "confidenceScore": 1.0
                    }
                ],
                "learnedSemanticTypes": null,
                "modelIds": null
            },
            {
                "id": "HN91637",
                "label": {
                    "uri": "HN91637",
                    "rdfsLabel": null
                },
                "type": "ColumnNode",
                "hNodeId": "HN91637",
                "columnName": "ObjectIdURI",
                "rdfLiteralType": null,
                "language": "",
                "userSemanticTypes": [
                    {
                        "hNodeId": "HN91637",
                        "domain": {
                            "uri": "http://www.cidoc-crm.org/cidoc-crm/E42_Identifier",
                            "rdfsLabel": null
                        },
                        "type": {
                            "uri": "http://isi.edu/integration/karma/dev#classLink",
                            "rdfsLabel": null
                        },
                        "origin": "User",
                        "confidenceScore": 1.0
                    },
                    {
                        "hNodeId": "HN91637",
                        "domain": {
                            "uri": "http://www.cidoc-crm.org/cidoc-crm/E42_Identifier",
                            "rdfsLabel": null
                        },
                        "type": {
                            "uri": "http://isi.edu/integration/karma/dev#classLink",
                            "rdfsLabel": null
                        },
                        "origin": "User",
                        "confidenceScore": 1.0
                    }
                ],
                "learnedSemanticTypes": null,
                "modelIds": null
            },
            {
                "id": "HN84669",
                "label": {
                    "uri": "HN84669",
                    "rdfsLabel": null
                },
                "type": "ColumnNode",
                "hNodeId": "HN84669",
                "columnName": "MediumURI",
                "rdfLiteralType": null,
                "language": "",
                "userSemanticTypes": [
                    {
                        "hNodeId": "HN84669",
                        "domain": {
                            "uri": "http://www.cidoc-crm.org/cidoc-crm/E33_Linguistic_Object",
                            "rdfsLabel": null
                        },
                        "type": {
                            "uri": "http://isi.edu/integration/karma/dev#classLink",
                            "rdfsLabel": null
                        },
                        "origin": "User",
                        "confidenceScore": 1.0
                    },
                    {
                        "hNodeId": "HN84669",
                        "domain": {
                            "uri": "http://www.cidoc-crm.org/cidoc-crm/E33_Linguistic_Object",
                            "rdfsLabel": null
                        },
                        "type": {
                            "uri": "http://isi.edu/integration/karma/dev#classLink",
                            "rdfsLabel": null
                        },
                        "origin": "User",
                        "confidenceScore": 1.0
                    }
                ],
                "learnedSemanticTypes": null,
                "modelIds": null
            },
            {
                "id": "HN47537",
                "label": {
                    "uri": "HN47537",
                    "rdfsLabel": null
                },
                "type": "ColumnNode",
                "hNodeId": "HN47537",
                "columnName": "ObjectNumber",
                "rdfLiteralType": null,
                "language": "",
                "userSemanticTypes": [
                    {
                        "hNodeId": "HN47537",
                        "domain": {
                            "uri": "http://www.cidoc-crm.org/cidoc-crm/E42_Identifier",
                            "rdfsLabel": null
                        },
                        "type": {
                            "uri": "http://www.w3.org/1999/02/22-rdf-syntax-ns#value",
                            "rdfsLabel": null
                        },
                        "origin": "User",
                        "confidenceScore": 1.0
                    },
                    {
                        "hNodeId": "HN47537",
                        "domain": {
                            "uri": "http://www.cidoc-crm.org/cidoc-crm/E42_Identifier",
                            "rdfsLabel": null
                        },
                        "type": {
                            "uri": "http://www.w3.org/1999/02/22-rdf-syntax-ns#value",
                            "rdfsLabel": null
                        },
                        "origin": "User",
                        "confidenceScore": 1.0
                    }
                ],
                "learnedSemanticTypes": null,
                "modelIds": null
            },
            {
                "id": "HN92441",
                "label": {
                    "uri": "HN92441",
                    "rdfsLabel": null
                },
                "type": "ColumnNode",
                "hNodeId": "HN92441",
                "columnName": "ObjectIdLabel",
                "rdfLiteralType": null,
                "language": "",
                "userSemanticTypes": [
                    {
                        "hNodeId": "HN92441",
                        "domain": {
                            "uri": "http://www.cidoc-crm.org/cidoc-crm/E42_Identifier",
                            "rdfsLabel": null
                        },
                        "type": {
                            "uri": "http://www.w3.org/2000/01/rdf-schema#label",
                            "rdfsLabel": null
                        },
                        "origin": "User",
                        "confidenceScore": 1.0
                    },
                    {
                        "hNodeId": "HN92441",
                        "domain": {
                            "uri": "http://www.cidoc-crm.org/cidoc-crm/E42_Identifier",
                            "rdfsLabel": null
                        },
                        "type": {
                            "uri": "http://www.w3.org/2000/01/rdf-schema#label",
                            "rdfsLabel": null
                        },
                        "origin": "User",
                        "confidenceScore": 1.0
                    }
                ],
                "learnedSemanticTypes": null,
                "modelIds": null
            },
            {
                "id": "HN47517",
                "label": {
                    "uri": "HN47517",
                    "rdfsLabel": null
                },
                "type": "ColumnNode",
                "hNodeId": "HN47517",
                "columnName": "Classification",
                "rdfLiteralType": null,
                "language": "",
                "userSemanticTypes": [
                    {
                        "hNodeId": "HN47517",
                        "domain": {
                            "uri": "http://www.cidoc-crm.org/cidoc-crm/E55_Type",
                            "rdfsLabel": null
                        },
                        "type": {
                            "uri": "http://www.w3.org/2000/01/rdf-schema#label",
                            "rdfsLabel": null
                        },
                        "origin": "User",
                        "confidenceScore": 1.0
                    },
                    {
                        "hNodeId": "HN47517",
                        "domain": {
                            "uri": "http://www.cidoc-crm.org/cidoc-crm/E55_Type",
                            "rdfsLabel": null
                        },
                        "type": {
                            "uri": "http://www.w3.org/2000/01/rdf-schema#label",
                            "rdfsLabel": null
                        },
                        "origin": "User",
                        "confidenceScore": 1.0
                    }
                ],
                "learnedSemanticTypes": null,
                "modelIds": null
            },
            {
                "id": "HN47571",
                "label": {
                    "uri": "HN47571",
                    "rdfsLabel": null
                },
                "type": "ColumnNode",
                "hNodeId": "HN47571",
                "columnName": "ResourceURL",
                "rdfLiteralType": null,
                "language": "",
                "userSemanticTypes": [
                    {
                        "hNodeId": "HN47571",
                        "domain": {
                            "uri": "http://xmlns.com/foaf/0.1/Document",
                            "rdfsLabel": null
                        },
                        "type": {
                            "uri": "http://www.w3.org/2000/01/rdf-schema#label",
                            "rdfsLabel": null
                        },
                        "origin": "User",
                        "confidenceScore": 1.0
                    },
                    {
                        "hNodeId": "HN47571",
                        "domain": {
                            "uri": "http://xmlns.com/foaf/0.1/Document",
                            "rdfsLabel": null
                        },
                        "type": {
                            "uri": "http://www.w3.org/2000/01/rdf-schema#label",
                            "rdfsLabel": null
                        },
                        "origin": "User",
                        "confidenceScore": 1.0
                    }
                ],
                "learnedSemanticTypes": null,
                "modelIds": null
            },
            {
                "id": "HN93245",
                "label": {
                    "uri": "HN93245",
                    "rdfsLabel": null
                },
                "type": "ColumnNode",
                "hNodeId": "HN93245",
                "columnName": "ObjectNoURI",
                "rdfLiteralType": null,
                "language": "",
                "userSemanticTypes": [
                    {
                        "hNodeId": "HN93245",
                        "domain": {
                            "uri": "http://www.cidoc-crm.org/cidoc-crm/E42_Identifier",
                            "rdfsLabel": null
                        },
                        "type": {
                            "uri": "http://isi.edu/integration/karma/dev#classLink",
                            "rdfsLabel": null
                        },
                        "origin": "User",
                        "confidenceScore": 1.0
                    },
                    {
                        "hNodeId": "HN93245",
                        "domain": {
                            "uri": "http://www.cidoc-crm.org/cidoc-crm/E42_Identifier",
                            "rdfsLabel": null
                        },
                        "type": {
                            "uri": "http://isi.edu/integration/karma/dev#classLink",
                            "rdfsLabel": null
                        },
                        "origin": "User",
                        "confidenceScore": 1.0
                    }
                ],
                "learnedSemanticTypes": null,
                "modelIds": null
            },
            {
                "id": "HN81451",
                "label": {
                    "uri": "HN81451",
                    "rdfsLabel": null
                },
                "type": "ColumnNode",
                "hNodeId": "HN81451",
                "columnName": "ClassificationEventURI",
                "rdfLiteralType": null,
                "language": "",
                "userSemanticTypes": [
                    {
                        "hNodeId": "HN81451",
                        "domain": {
                            "uri": "http://www.cidoc-crm.org/cidoc-crm/E17_Type_Assignment",
                            "rdfsLabel": null
                        },
                        "type": {
                            "uri": "http://isi.edu/integration/karma/dev#classLink",
                            "rdfsLabel": null
                        },
                        "origin": "User",
                        "confidenceScore": 1.0
                    },
                    {
                        "hNodeId": "HN81451",
                        "domain": {
                            "uri": "http://www.cidoc-crm.org/cidoc-crm/E17_Type_Assignment",
                            "rdfsLabel": null
                        },
                        "type": {
                            "uri": "http://isi.edu/integration/karma/dev#classLink",
                            "rdfsLabel": null
                        },
                        "origin": "User",
                        "confidenceScore": 1.0
                    }
                ],
                "learnedSemanticTypes": null,
                "modelIds": null
            },
            {
                "id": "HN82255",
                "label": {
                    "uri": "HN82255",
                    "rdfsLabel": null
                },
                "type": "ColumnNode",
                "hNodeId": "HN82255",
                "columnName": "CreditLineURI",
                "rdfLiteralType": null,
                "language": "",
                "userSemanticTypes": [
                    {
                        "hNodeId": "HN82255",
                        "domain": {
                            "uri": "http://www.cidoc-crm.org/cidoc-crm/E33_Linguistic_Object",
                            "rdfsLabel": null
                        },
                        "type": {
                            "uri": "http://isi.edu/integration/karma/dev#classLink",
                            "rdfsLabel": null
                        },
                        "origin": "User",
                        "confidenceScore": 1.0
                    },
                    {
                        "hNodeId": "HN82255",
                        "domain": {
                            "uri": "http://www.cidoc-crm.org/cidoc-crm/E33_Linguistic_Object",
                            "rdfsLabel": null
                        },
                        "type": {
                            "uri": "http://isi.edu/integration/karma/dev#classLink",
                            "rdfsLabel": null
                        },
                        "origin": "User",
                        "confidenceScore": 1.0
                    }
                ],
                "learnedSemanticTypes": null,
                "modelIds": null
            },
            {
                "id": "HN47519",
                "label": {
                    "uri": "HN47519",
                    "rdfsLabel": null
                },
                "type": "ColumnNode",
                "hNodeId": "HN47519",
                "columnName": "CreditLine",
                "rdfLiteralType": null,
                "language": "",
                "userSemanticTypes": [
                    {
                        "hNodeId": "HN47519",
                        "domain": {
                            "uri": "http://www.cidoc-crm.org/cidoc-crm/E33_Linguistic_Object",
                            "rdfsLabel": null
                        },
                        "type": {
                            "uri": "http://www.w3.org/1999/02/22-rdf-syntax-ns#value",
                            "rdfsLabel": null
                        },
                        "origin": "User",
                        "confidenceScore": 1.0
                    },
                    {
                        "hNodeId": "HN47519",
                        "domain": {
                            "uri": "http://www.cidoc-crm.org/cidoc-crm/E33_Linguistic_Object",
                            "rdfsLabel": null
                        },
                        "type": {
                            "uri": "http://www.w3.org/1999/02/22-rdf-syntax-ns#value",
                            "rdfsLabel": null
                        },
                        "origin": "User",
                        "confidenceScore": 1.0
                    }
                ],
                "learnedSemanticTypes": null,
                "modelIds": null
            },
            {
                "id": "HN83061",
                "label": {
                    "uri": "HN83061",
                    "rdfsLabel": null
                },
                "type": "ColumnNode",
                "hNodeId": "HN83061",
                "columnName": "ProductionURI",
                "rdfLiteralType": null,
                "language": "",
                "userSemanticTypes": [
                    {
                        "hNodeId": "HN83061",
                        "domain": {
                            "uri": "http://www.cidoc-crm.org/cidoc-crm/E12_Production",
                            "rdfsLabel": null
                        },
                        "type": {
                            "uri": "http://isi.edu/integration/karma/dev#classLink",
                            "rdfsLabel": null
                        },
                        "origin": "User",
                        "confidenceScore": 1.0
                    },
                    {
                        "hNodeId": "HN83061",
                        "domain": {
                            "uri": "http://www.cidoc-crm.org/cidoc-crm/E12_Production",
                            "rdfsLabel": null
                        },
                        "type": {
                            "uri": "http://isi.edu/integration/karma/dev#classLink",
                            "rdfsLabel": null
                        },
                        "origin": "User",
                        "confidenceScore": 1.0
                    }
                ],
                "learnedSemanticTypes": null,
                "modelIds": null
            },
            {
                "id": "HN89223",
                "label": {
                    "uri": "HN89223",
                    "rdfsLabel": null
                },
                "type": "ColumnNode",
                "hNodeId": "HN89223",
                "columnName": "DescriptionURI",
                "rdfLiteralType": null,
                "language": "",
                "userSemanticTypes": [
                    {
                        "hNodeId": "HN89223",
                        "domain": {
                            "uri": "http://www.cidoc-crm.org/cidoc-crm/E33_Linguistic_Object",
                            "rdfsLabel": null
                        },
                        "type": {
                            "uri": "http://isi.edu/integration/karma/dev#classLink",
                            "rdfsLabel": null
                        },
                        "origin": "User",
                        "confidenceScore": 1.0
                    },
                    {
                        "hNodeId": "HN89223",
                        "domain": {
                            "uri": "http://www.cidoc-crm.org/cidoc-crm/E33_Linguistic_Object",
                            "rdfsLabel": null
                        },
                        "type": {
                            "uri": "http://isi.edu/integration/karma/dev#classLink",
                            "rdfsLabel": null
                        },
                        "origin": "User",
                        "confidenceScore": 1.0
                    }
                ],
                "learnedSemanticTypes": null,
                "modelIds": null
            },
            {
                "id": "HN79843",
                "label": {
                    "uri": "HN79843",
                    "rdfsLabel": null
                },
                "type": "ColumnNode",
                "hNodeId": "HN79843",
                "columnName": "ObjectURI",
                "rdfLiteralType": null,
                "language": "",
                "userSemanticTypes": [
                    {
                        "hNodeId": "HN79843",
                        "domain": {
                            "uri": "http://www.cidoc-crm.org/cidoc-crm/E22_Man-Made_Object",
                            "rdfsLabel": null
                        },
                        "type": {
                            "uri": "http://isi.edu/integration/karma/dev#classLink",
                            "rdfsLabel": null
                        },
                        "origin": "User",
                        "confidenceScore": 1.0
                    },
                    {
                        "hNodeId": "HN79843",
                        "domain": {
                            "uri": "http://www.cidoc-crm.org/cidoc-crm/E22_Man-Made_Object",
                            "rdfsLabel": null
                        },
                        "type": {
                            "uri": "http://isi.edu/integration/karma/dev#classLink",
                            "rdfsLabel": null
                        },
                        "origin": "User",
                        "confidenceScore": 1.0
                    }
                ],
                "learnedSemanticTypes": null,
                "modelIds": null
            },
            {
                "id": "HN87348",
                "label": {
                    "uri": "HN87348",
                    "rdfsLabel": null
                },
                "type": "ColumnNode",
                "hNodeId": "HN87348",
                "columnName": "MediumLodTerm",
                "rdfLiteralType": null,
                "language": "",
                "userSemanticTypes": [
                    {
                        "hNodeId": "HN87348",
                        "domain": {
                            "uri": "http://www.cidoc-crm.org/cidoc-crm/E57_Material",
                            "rdfsLabel": null
                        },
                        "type": {
                            "uri": "http://www.w3.org/2004/02/skos/core#broadMatch",
                            "rdfsLabel": "has broader match"
                        },
                        "origin": "User",
                        "confidenceScore": 1.0
                    },
                    {
                        "hNodeId": "HN87348",
                        "domain": {
                            "uri": "http://www.cidoc-crm.org/cidoc-crm/E57_Material",
                            "rdfsLabel": null
                        },
                        "type": {
                            "uri": "http://www.w3.org/2004/02/skos/core#broadMatch",
                            "rdfsLabel": "has broader match"
                        },
                        "origin": "User",
                        "confidenceScore": 1.0
                    }
                ],
                "learnedSemanticTypes": null,
                "modelIds": null
            },
            {
                "id": "HN47525",
                "label": {
                    "uri": "HN47525",
                    "rdfsLabel": null
                },
                "type": "ColumnNode",
                "hNodeId": "HN47525",
                "columnName": "DateBegin",
                "rdfLiteralType": null,
                "language": "",
                "userSemanticTypes": [
                    {
                        "hNodeId": "HN47525",
                        "domain": {
                            "uri": "http://www.cidoc-crm.org/cidoc-crm/E52_Time-Span",
                            "rdfsLabel": null
                        },
                        "type": {
                            "uri": "http://www.cidoc-crm.org/cidoc-crm/P82a_begin_of_the_begin",
                            "rdfsLabel": "begin of the begin"
                        },
                        "origin": "User",
                        "confidenceScore": 1.0
                    },
                    {
                        "hNodeId": "HN47525",
                        "domain": {
                            "uri": "http://www.cidoc-crm.org/cidoc-crm/E52_Time-Span",
                            "rdfsLabel": null
                        },
                        "type": {
                            "uri": "http://www.cidoc-crm.org/cidoc-crm/P82a_begin_of_the_begin",
                            "rdfsLabel": "begin of the begin"
                        },
                        "origin": "User",
                        "confidenceScore": 1.0
                    }
                ],
                "learnedSemanticTypes": null,
                "modelIds": null
            },
            {
                "id": "HN47544",
                "label": {
                    "uri": "HN47544",
                    "rdfsLabel": null
                },
                "type": "ColumnNode",
                "hNodeId": "HN47544",
                "columnName": "Medium",
                "rdfLiteralType": null,
                "language": "",
                "userSemanticTypes": [
                    {
                        "hNodeId": "HN47544",
                        "domain": {
                            "uri": "http://www.cidoc-crm.org/cidoc-crm/E33_Linguistic_Object",
                            "rdfsLabel": null
                        },
                        "type": {
                            "uri": "http://www.w3.org/1999/02/22-rdf-syntax-ns#value",
                            "rdfsLabel": null
                        },
                        "origin": "User",
                        "confidenceScore": 1.0
                    },
                    {
                        "hNodeId": "HN47544",
                        "domain": {
                            "uri": "http://www.cidoc-crm.org/cidoc-crm/E33_Linguistic_Object",
                            "rdfsLabel": null
                        },
                        "type": {
                            "uri": "http://www.w3.org/1999/02/22-rdf-syntax-ns#value",
                            "rdfsLabel": null
                        },
                        "origin": "User",
                        "confidenceScore": 1.0
                    }
                ],
                "learnedSemanticTypes": null,
                "modelIds": null
            },
            {
                "id": "HN94050",
                "label": {
                    "uri": "HN94050",
                    "rdfsLabel": null
                },
                "type": "ColumnNode",
                "hNodeId": "HN94050",
                "columnName": "OwnerLabel",
                "rdfLiteralType": null,
                "language": "",
                "userSemanticTypes": [
                    {
                        "hNodeId": "HN94050",
                        "domain": {
                            "uri": "http://www.cidoc-crm.org/cidoc-crm/E40_Legal_Body",
                            "rdfsLabel": null
                        },
                        "type": {
                            "uri": "http://www.w3.org/2000/01/rdf-schema#label",
                            "rdfsLabel": null
                        },
                        "origin": "User",
                        "confidenceScore": 1.0
                    },
                    {
                        "hNodeId": "HN94050",
                        "domain": {
                            "uri": "http://www.cidoc-crm.org/cidoc-crm/E40_Legal_Body",
                            "rdfsLabel": null
                        },
                        "type": {
                            "uri": "http://www.w3.org/2000/01/rdf-schema#label",
                            "rdfsLabel": null
                        },
                        "origin": "User",
                        "confidenceScore": 1.0
                    }
                ],
                "learnedSemanticTypes": null,
                "modelIds": null
            },
            {
                "id": "HN47569",
                "label": {
                    "uri": "HN47569",
                    "rdfsLabel": null
                },
                "type": "ColumnNode",
                "hNodeId": "HN47569",
                "columnName": "PublicDescription",
                "rdfLiteralType": null,
                "language": "",
                "userSemanticTypes": [
                    {
                        "hNodeId": "HN47569",
                        "domain": {
                            "uri": "http://www.cidoc-crm.org/cidoc-crm/E33_Linguistic_Object",
                            "rdfsLabel": null
                        },
                        "type": {
                            "uri": "http://www.w3.org/1999/02/22-rdf-syntax-ns#value",
                            "rdfsLabel": null
                        },
                        "origin": "User",
                        "confidenceScore": 1.0
                    },
                    {
                        "hNodeId": "HN47569",
                        "domain": {
                            "uri": "http://www.cidoc-crm.org/cidoc-crm/E33_Linguistic_Object",
                            "rdfsLabel": null
                        },
                        "type": {
                            "uri": "http://www.w3.org/1999/02/22-rdf-syntax-ns#value",
                            "rdfsLabel": null
                        },
                        "origin": "User",
                        "confidenceScore": 1.0
                    }
                ],
                "learnedSemanticTypes": null,
                "modelIds": null
            },
            {
                "id": "HN80647",
                "label": {
                    "uri": "HN80647",
                    "rdfsLabel": null
                },
                "type": "ColumnNode",
                "hNodeId": "HN80647",
                "columnName": "ClassificationURI",
                "rdfLiteralType": null,
                "language": "",
                "userSemanticTypes": [
                    {
                        "hNodeId": "HN80647",
                        "domain": {
                            "uri": "http://www.cidoc-crm.org/cidoc-crm/E55_Type",
                            "rdfsLabel": null
                        },
                        "type": {
                            "uri": "http://isi.edu/integration/karma/dev#classLink",
                            "rdfsLabel": null
                        },
                        "origin": "User",
                        "confidenceScore": 1.0
                    },
                    {
                        "hNodeId": "HN80647",
                        "domain": {
                            "uri": "http://www.cidoc-crm.org/cidoc-crm/E55_Type",
                            "rdfsLabel": null
                        },
                        "type": {
                            "uri": "http://isi.edu/integration/karma/dev#classLink",
                            "rdfsLabel": null
                        },
                        "origin": "User",
                        "confidenceScore": 1.0
                    }
                ],
                "learnedSemanticTypes": null,
                "modelIds": null
            },
            {
                "id": "HN90027",
                "label": {
                    "uri": "HN90027",
                    "rdfsLabel": null
                },
                "type": "ColumnNode",
                "hNodeId": "HN90027",
                "columnName": "UrlURI",
                "rdfLiteralType": null,
                "language": "",
                "userSemanticTypes": [
                    {
                        "hNodeId": "HN90027",
                        "domain": {
                            "uri": "http://xmlns.com/foaf/0.1/Document",
                            "rdfsLabel": null
                        },
                        "type": {
                            "uri": "http://isi.edu/integration/karma/dev#classLink",
                            "rdfsLabel": null
                        },
                        "origin": "User",
                        "confidenceScore": 1.0
                    },
                    {
                        "hNodeId": "HN90027",
                        "domain": {
                            "uri": "http://xmlns.com/foaf/0.1/Document",
                            "rdfsLabel": null
                        },
                        "type": {
                            "uri": "http://isi.edu/integration/karma/dev#classLink",
                            "rdfsLabel": null
                        },
                        "origin": "User",
                        "confidenceScore": 1.0
                    }
                ],
                "learnedSemanticTypes": null,
                "modelIds": null
            },
            {
                "id": "HN47527",
                "label": {
                    "uri": "HN47527",
                    "rdfsLabel": null
                },
                "type": "ColumnNode",
                "hNodeId": "HN47527",
                "columnName": "DateEnd",
                "rdfLiteralType": null,
                "language": "",
                "userSemanticTypes": [
                    {
                        "hNodeId": "HN47527",
                        "domain": {
                            "uri": "http://www.cidoc-crm.org/cidoc-crm/E52_Time-Span",
                            "rdfsLabel": null
                        },
                        "type": {
                            "uri": "http://www.cidoc-crm.org/cidoc-crm/P82b_end_of_the_end",
                            "rdfsLabel": "end of the end"
                        },
                        "origin": "User",
                        "confidenceScore": 1.0
                    },
                    {
                        "hNodeId": "HN47527",
                        "domain": {
                            "uri": "http://www.cidoc-crm.org/cidoc-crm/E52_Time-Span",
                            "rdfsLabel": null
                        },
                        "type": {
                            "uri": "http://www.cidoc-crm.org/cidoc-crm/P82b_end_of_the_end",
                            "rdfsLabel": "end of the end"
                        },
                        "origin": "User",
                        "confidenceScore": 1.0
                    }
                ],
                "learnedSemanticTypes": null,
                "modelIds": null
            },
            {
                "id": "HN47529",
                "label": {
                    "uri": "HN47529",
                    "rdfsLabel": null
                },
                "type": "ColumnNode",
                "hNodeId": "HN47529",
                "columnName": "Dated",
                "rdfLiteralType": null,
                "language": "",
                "userSemanticTypes": [
                    {
                        "hNodeId": "HN47529",
                        "domain": {
                            "uri": "http://www.cidoc-crm.org/cidoc-crm/E52_Time-Span",
                            "rdfsLabel": null
                        },
                        "type": {
                            "uri": "http://www.w3.org/2000/01/rdf-schema#label",
                            "rdfsLabel": null
                        },
                        "origin": "User",
                        "confidenceScore": 1.0
                    },
                    {
                        "hNodeId": "HN47529",
                        "domain": {
                            "uri": "http://www.cidoc-crm.org/cidoc-crm/E52_Time-Span",
                            "rdfsLabel": null
                        },
                        "type": {
                            "uri": "http://www.w3.org/2000/01/rdf-schema#label",
                            "rdfsLabel": null
                        },
                        "origin": "User",
                        "confidenceScore": 1.0
                    }
                ],
                "learnedSemanticTypes": null,
                "modelIds": null
            },
            {
                "id": "HN83865",
                "label": {
                    "uri": "HN83865",
                    "rdfsLabel": null
                },
                "type": "ColumnNode",
                "hNodeId": "HN83865",
                "columnName": "ProductionTimespanURI",
                "rdfLiteralType": null,
                "language": "",
                "userSemanticTypes": [
                    {
                        "hNodeId": "HN83865",
                        "domain": {
                            "uri": "http://www.cidoc-crm.org/cidoc-crm/E52_Time-Span",
                            "rdfsLabel": null
                        },
                        "type": {
                            "uri": "http://isi.edu/integration/karma/dev#classLink",
                            "rdfsLabel": null
                        },
                        "origin": "User",
                        "confidenceScore": 1.0
                    },
                    {
                        "hNodeId": "HN83865",
                        "domain": {
                            "uri": "http://www.cidoc-crm.org/cidoc-crm/E52_Time-Span",
                            "rdfsLabel": null
                        },
                        "type": {
                            "uri": "http://isi.edu/integration/karma/dev#classLink",
                            "rdfsLabel": null
                        },
                        "origin": "User",
                        "confidenceScore": 1.0
                    }
                ],
                "learnedSemanticTypes": null,
                "modelIds": null
            },
            {
                "id": "HN90833",
                "label": {
                    "uri": "HN90833",
                    "rdfsLabel": null
                },
                "type": "ColumnNode",
                "hNodeId": "HN90833",
                "columnName": "CurrentOwnerURI",
                "rdfLiteralType": null,
                "language": "",
                "userSemanticTypes": [
                    {
                        "hNodeId": "HN90833",
                        "domain": {
                            "uri": "http://www.cidoc-crm.org/cidoc-crm/E40_Legal_Body",
                            "rdfsLabel": null
                        },
                        "type": {
                            "uri": "http://isi.edu/integration/karma/dev#classLink",
                            "rdfsLabel": null
                        },
                        "origin": "User",
                        "confidenceScore": 1.0
                    },
                    {
                        "hNodeId": "HN90833",
                        "domain": {
                            "uri": "http://www.cidoc-crm.org/cidoc-crm/E40_Legal_Body",
                            "rdfsLabel": null
                        },
                        "type": {
                            "uri": "http://isi.edu/integration/karma/dev#classLink",
                            "rdfsLabel": null
                        },
                        "origin": "User",
                        "confidenceScore": 1.0
                    }
                ],
                "learnedSemanticTypes": null,
                "modelIds": null
            },
            {
                "id": "http://vocab.getty.edu/aat/3004046702",
                "label": {
                    "uri": "",
                    "rdfsLabel": null
                },
                "type": "LiteralNode",
                "value": "http://vocab.getty.edu/aat/300404670",
                "datatype": {
                    "uri": "",
                    "rdfsLabel": null
                },
                "language": "",
                "isUri": "true",
                "modelIds": null
            },
            {
                "id": "http://vocab.getty.edu/aat/3000800911",
                "label": {
                    "uri": "",
                    "rdfsLabel": null
                },
                "type": "LiteralNode",
                "value": "http://vocab.getty.edu/aat/300080091",
                "datatype": {
                    "uri": "",
                    "rdfsLabel": null
                },
                "language": "",
                "isUri": "true",
                "modelIds": null
            },
            {
                "id": "http://vocab.getty.edu/ulan/5002791101",
                "label": {
                    "uri": "",
                    "rdfsLabel": null
                },
                "type": "LiteralNode",
                "value": "http://vocab.getty.edu/ulan/500279110",
                "datatype": {
                    "uri": "",
                    "rdfsLabel": null
                },
                "language": "",
                "isUri": "true",
                "modelIds": null
            },
            {
                "id": "http://vocab.getty.edu/aat/3004046211",
                "label": {
                    "uri": "",
                    "rdfsLabel": null
                },
                "type": "LiteralNode",
                "value": "http://vocab.getty.edu/aat/300404621",
                "datatype": {
                    "uri": "",
                    "rdfsLabel": null
                },
                "language": "",
                "isUri": "true",
                "modelIds": null
            },
            {
                "id": "http://vocab.getty.edu/aat/3001798691",
                "label": {
                    "uri": "",
                    "rdfsLabel": null
                },
                "type": "LiteralNode",
                "value": "http://vocab.getty.edu/aat/300179869",
                "datatype": {
                    "uri": "",
                    "rdfsLabel": null
                },
                "language": "",
                "isUri": "true",
                "modelIds": null
            },
            {
                "id": "http://vocab.getty.edu/aat/3004046701",
                "label": {
                    "uri": "",
                    "rdfsLabel": null
                },
                "type": "LiteralNode",
                "value": "http://vocab.getty.edu/aat/300404670",
                "datatype": {
                    "uri": "",
                    "rdfsLabel": null
                },
                "language": "",
                "isUri": "true",
                "modelIds": null
            },
            {
                "id": "http://vocab.getty.edu/aat/3002642371",
                "label": {
                    "uri": "",
                    "rdfsLabel": null
                },
                "type": "LiteralNode",
                "value": "http://vocab.getty.edu/aat/300264237",
                "datatype": {
                    "uri": "",
                    "rdfsLabel": null
                },
                "language": "",
                "isUri": "true",
                "modelIds": null
            },
            {
                "id": "http://vocab.getty.edu/aat/3000266871",
                "label": {
                    "uri": "",
                    "rdfsLabel": null
                },
                "type": "LiteralNode",
                "value": "http://vocab.getty.edu/aat/300026687",
                "datatype": {
                    "uri": "",
                    "rdfsLabel": null
                },
                "language": "",
                "isUri": "true",
                "modelIds": null
            }
        ],
        "links": [
            {
                "id": "http://www.cidoc-crm.org/cidoc-crm/E12_Production1---http://www.cidoc-crm.org/cidoc-crm/P4_has_time-span---http://www.cidoc-crm.org/cidoc-crm/E52_Time-Span1",
                "weight": 0.009999999776482582,
                "type": "ObjectPropertyLink",
                "label": {
                    "uri": "http://www.cidoc-crm.org/cidoc-crm/P4_has_time-span",
                    "rdfsLabel": null
                },
                "objectPropertyType": "Indirect",
                "status": "ForcedByUser",
                "keyInfo": "None",
                "modelIds": null
            },
            {
                "id": "http://www.cidoc-crm.org/cidoc-crm/E17_Type_Assignment1---http://www.cidoc-crm.org/cidoc-crm/P42_assigned---http://www.cidoc-crm.org/cidoc-crm/E55_Type1",
                "weight": 0.009999999776482582,
                "type": "ObjectPropertyLink",
                "label": {
                    "uri": "http://www.cidoc-crm.org/cidoc-crm/P42_assigned",
                    "rdfsLabel": "assigned"
                },
                "objectPropertyType": "Direct",
                "status": "ForcedByUser",
                "keyInfo": "None",
                "modelIds": null
            },
            {
                "id": "http://www.cidoc-crm.org/cidoc-crm/E22_Man-Made_Object1---http://www.cidoc-crm.org/cidoc-crm/P108i_was_produced_by---http://www.cidoc-crm.org/cidoc-crm/E12_Production1",
                "weight": 0.009999999776482582,
                "type": "ObjectPropertyLink",
                "label": {
                    "uri": "http://www.cidoc-crm.org/cidoc-crm/P108i_was_produced_by",
                    "rdfsLabel": "was produced by"
                },
                "objectPropertyType": "Indirect",
                "status": "ForcedByUser",
                "keyInfo": "None",
                "modelIds": null
            },
            {
                "id": "http://www.cidoc-crm.org/cidoc-crm/E22_Man-Made_Object1---http://www.cidoc-crm.org/cidoc-crm/P41i_was_classified_by---http://www.cidoc-crm.org/cidoc-crm/E17_Type_Assignment1",
                "weight": 0.009999999776482582,
                "type": "ObjectPropertyLink",
                "label": {
                    "uri": "http://www.cidoc-crm.org/cidoc-crm/P41i_was_classified_by",
                    "rdfsLabel": "was classified by"
                },
                "objectPropertyType": "Indirect",
                "status": "ForcedByUser",
                "keyInfo": "None",
                "modelIds": null
            },
            {
                "id": "http://www.cidoc-crm.org/cidoc-crm/E22_Man-Made_Object1---http://www.cidoc-crm.org/cidoc-crm/P67i_is_referred_to_by---http://www.cidoc-crm.org/cidoc-crm/E33_Linguistic_Object1",
                "weight": 0.009999999776482582,
                "type": "ObjectPropertyLink",
                "label": {
                    "uri": "http://www.cidoc-crm.org/cidoc-crm/P67i_is_referred_to_by",
                    "rdfsLabel": null
                },
                "objectPropertyType": "Indirect",
                "status": "ForcedByUser",
                "keyInfo": "None",
                "modelIds": null
            },
            {
                "id": "http://www.cidoc-crm.org/cidoc-crm/E22_Man-Made_Object1---http://www.cidoc-crm.org/cidoc-crm/P67i_is_referred_to_by---http://www.cidoc-crm.org/cidoc-crm/E33_Linguistic_Object2",
                "weight": 0.009999999776482582,
                "type": "ObjectPropertyLink",
                "label": {
                    "uri": "http://www.cidoc-crm.org/cidoc-crm/P67i_is_referred_to_by",
                    "rdfsLabel": null
                },
                "objectPropertyType": "Indirect",
                "status": "ForcedByUser",
                "keyInfo": "None",
                "modelIds": null
            },
            {
                "id": "http://www.cidoc-crm.org/cidoc-crm/E22_Man-Made_Object1---http://www.cidoc-crm.org/cidoc-crm/P129i_is_subject_of---http://www.cidoc-crm.org/cidoc-crm/E33_Linguistic_Object3",
                "weight": 0.009999999776482582,
                "type": "ObjectPropertyLink",
                "label": {
                    "uri": "http://www.cidoc-crm.org/cidoc-crm/P129i_is_subject_of",
                    "rdfsLabel": null
                },
                "objectPropertyType": "Indirect",
                "status": "ForcedByUser",
                "keyInfo": "None",
                "modelIds": null
            },
            {
                "id": "http://www.cidoc-crm.org/cidoc-crm/E22_Man-Made_Object1---http://www.cidoc-crm.org/cidoc-crm/P52_has_current_owner---http://www.cidoc-crm.org/cidoc-crm/E40_Legal_Body1",
                "weight": 0.009999999776482582,
                "type": "ObjectPropertyLink",
                "label": {
                    "uri": "http://www.cidoc-crm.org/cidoc-crm/P52_has_current_owner",
                    "rdfsLabel": null
                },
                "objectPropertyType": "Indirect",
                "status": "ForcedByUser",
                "keyInfo": "None",
                "modelIds": null
            },
            {
                "id": "http://www.cidoc-crm.org/cidoc-crm/E22_Man-Made_Object1---http://www.cidoc-crm.org/cidoc-crm/P1_is_identified_by---http://www.cidoc-crm.org/cidoc-crm/E42_Identifier1",
                "weight": 0.009999999776482582,
                "type": "ObjectPropertyLink",
                "label": {
                    "uri": "http://www.cidoc-crm.org/cidoc-crm/P1_is_identified_by",
                    "rdfsLabel": null
                },
                "objectPropertyType": "Indirect",
                "status": "ForcedByUser",
                "keyInfo": "None",
                "modelIds": null
            },
            {
                "id": "http://www.cidoc-crm.org/cidoc-crm/E22_Man-Made_Object1---http://www.cidoc-crm.org/cidoc-crm/P1_is_identified_by---http://www.cidoc-crm.org/cidoc-crm/E42_Identifier2",
                "weight": 0.009999999776482582,
                "type": "ObjectPropertyLink",
                "label": {
                    "uri": "http://www.cidoc-crm.org/cidoc-crm/P1_is_identified_by",
                    "rdfsLabel": null
                },
                "objectPropertyType": "Indirect",
                "status": "ForcedByUser",
                "keyInfo": "None",
                "modelIds": null
            },
            {
                "id": "http://www.cidoc-crm.org/cidoc-crm/E22_Man-Made_Object1---http://www.cidoc-crm.org/cidoc-crm/P45_consists_of---http://www.cidoc-crm.org/cidoc-crm/E57_Material1",
                "weight": 0.009999999776482582,
                "type": "ObjectPropertyLink",
                "label": {
                    "uri": "http://www.cidoc-crm.org/cidoc-crm/P45_consists_of",
                    "rdfsLabel": null
                },
                "objectPropertyType": "Indirect",
                "status": "ForcedByUser",
                "keyInfo": "None",
                "modelIds": null
            },
            {
                "id": "http://www.cidoc-crm.org/cidoc-crm/E22_Man-Made_Object1---http://xmlns.com/foaf/0.1/homepage---http://xmlns.com/foaf/0.1/Document1",
                "weight": 0.009999999776482582,
                "type": "ObjectPropertyLink",
                "label": {
                    "uri": "http://xmlns.com/foaf/0.1/homepage",
                    "rdfsLabel": null
                },
                "objectPropertyType": "WithOnlyRange",
                "status": "ForcedByUser",
                "keyInfo": "None",
                "modelIds": null
            },
            {
                "id": "http://www.cidoc-crm.org/cidoc-crm/E42_Identifier1---http://www.w3.org/1999/02/22-rdf-syntax-ns#value---HN47535",
                "weight": 0.01,
                "type": "DataPropertyLink",
                "label": {
                    "uri": "http://www.w3.org/1999/02/22-rdf-syntax-ns#value",
                    "rdfsLabel": null
                },
                "status": "ForcedByUser",
                "keyInfo": "None",
                "modelIds": null
            },
            {
                "id": "http://www.cidoc-crm.org/cidoc-crm/E57_Material1---http://www.w3.org/2004/02/skos/core#prefLabel---HN47555",
                "weight": 0.01,
                "type": "DataPropertyLink",
                "label": {
                    "uri": "http://www.w3.org/2004/02/skos/core#prefLabel",
                    "rdfsLabel": "preferred label"
                },
                "status": "ForcedByUser",
                "keyInfo": "None",
                "modelIds": null
            },
            {
                "id": "http://www.cidoc-crm.org/cidoc-crm/E57_Material1---http://isi.edu/integration/karma/dev#classLink---HN85473",
                "weight": 0.01,
                "type": "ClassInstanceLink",
                "label": {
                    "uri": "http://isi.edu/integration/karma/dev#classLink",
                    "rdfsLabel": null
                },
                "status": "ForcedByUser",
                "keyInfo": "UriOfInstance",
                "modelIds": null
            },
            {
                "id": "http://www.cidoc-crm.org/cidoc-crm/E42_Identifier1---http://isi.edu/integration/karma/dev#classLink---HN91637",
                "weight": 0.01,
                "type": "ClassInstanceLink",
                "label": {
                    "uri": "http://isi.edu/integration/karma/dev#classLink",
                    "rdfsLabel": null
                },
                "status": "ForcedByUser",
                "keyInfo": "UriOfInstance",
                "modelIds": null
            },
            {
                "id": "http://www.cidoc-crm.org/cidoc-crm/E33_Linguistic_Object2---http://isi.edu/integration/karma/dev#classLink---HN84669",
                "weight": 0.01,
                "type": "ClassInstanceLink",
                "label": {
                    "uri": "http://isi.edu/integration/karma/dev#classLink",
                    "rdfsLabel": null
                },
                "status": "ForcedByUser",
                "keyInfo": "UriOfInstance",
                "modelIds": null
            },
            {
                "id": "http://www.cidoc-crm.org/cidoc-crm/E42_Identifier2---http://www.w3.org/1999/02/22-rdf-syntax-ns#value---HN47537",
                "weight": 0.01,
                "type": "DataPropertyLink",
                "label": {
                    "uri": "http://www.w3.org/1999/02/22-rdf-syntax-ns#value",
                    "rdfsLabel": null
                },
                "status": "ForcedByUser",
                "keyInfo": "None",
                "modelIds": null
            },
            {
                "id": "http://www.cidoc-crm.org/cidoc-crm/E42_Identifier1---http://www.w3.org/2000/01/rdf-schema#label---HN92441",
                "weight": 0.01,
                "type": "DataPropertyLink",
                "label": {
                    "uri": "http://www.w3.org/2000/01/rdf-schema#label",
                    "rdfsLabel": null
                },
                "status": "ForcedByUser",
                "keyInfo": "None",
                "modelIds": null
            },
            {
                "id": "http://www.cidoc-crm.org/cidoc-crm/E55_Type1---http://www.w3.org/2000/01/rdf-schema#label---HN47517",
                "weight": 0.01,
                "type": "DataPropertyLink",
                "label": {
                    "uri": "http://www.w3.org/2000/01/rdf-schema#label",
                    "rdfsLabel": null
                },
                "status": "ForcedByUser",
                "keyInfo": "None",
                "modelIds": null
            },
            {
                "id": "http://xmlns.com/foaf/0.1/Document1---http://www.w3.org/2000/01/rdf-schema#label---HN47571",
                "weight": 0.01,
                "type": "DataPropertyLink",
                "label": {
                    "uri": "http://www.w3.org/2000/01/rdf-schema#label",
                    "rdfsLabel": null
                },
                "status": "ForcedByUser",
                "keyInfo": "None",
                "modelIds": null
            },
            {
                "id": "http://www.cidoc-crm.org/cidoc-crm/E42_Identifier2---http://isi.edu/integration/karma/dev#classLink---HN93245",
                "weight": 0.01,
                "type": "ClassInstanceLink",
                "label": {
                    "uri": "http://isi.edu/integration/karma/dev#classLink",
                    "rdfsLabel": null
                },
                "status": "ForcedByUser",
                "keyInfo": "UriOfInstance",
                "modelIds": null
            },
            {
                "id": "http://www.cidoc-crm.org/cidoc-crm/E17_Type_Assignment1---http://isi.edu/integration/karma/dev#classLink---HN81451",
                "weight": 0.01,
                "type": "ClassInstanceLink",
                "label": {
                    "uri": "http://isi.edu/integration/karma/dev#classLink",
                    "rdfsLabel": null
                },
                "status": "ForcedByUser",
                "keyInfo": "UriOfInstance",
                "modelIds": null
            },
            {
                "id": "http://www.cidoc-crm.org/cidoc-crm/E33_Linguistic_Object1---http://isi.edu/integration/karma/dev#classLink---HN82255",
                "weight": 0.01,
                "type": "ClassInstanceLink",
                "label": {
                    "uri": "http://isi.edu/integration/karma/dev#classLink",
                    "rdfsLabel": null
                },
                "status": "ForcedByUser",
                "keyInfo": "UriOfInstance",
                "modelIds": null
            },
            {
                "id": "http://www.cidoc-crm.org/cidoc-crm/E33_Linguistic_Object1---http://www.w3.org/1999/02/22-rdf-syntax-ns#value---HN47519",
                "weight": 0.01,
                "type": "DataPropertyLink",
                "label": {
                    "uri": "http://www.w3.org/1999/02/22-rdf-syntax-ns#value",
                    "rdfsLabel": null
                },
                "status": "ForcedByUser",
                "keyInfo": "None",
                "modelIds": null
            },
            {
                "id": "http://www.cidoc-crm.org/cidoc-crm/E12_Production1---http://isi.edu/integration/karma/dev#classLink---HN83061",
                "weight": 0.01,
                "type": "ClassInstanceLink",
                "label": {
                    "uri": "http://isi.edu/integration/karma/dev#classLink",
                    "rdfsLabel": null
                },
                "status": "ForcedByUser",
                "keyInfo": "UriOfInstance",
                "modelIds": null
            },
            {
                "id": "http://www.cidoc-crm.org/cidoc-crm/E33_Linguistic_Object3---http://isi.edu/integration/karma/dev#classLink---HN89223",
                "weight": 0.01,
                "type": "ClassInstanceLink",
                "label": {
                    "uri": "http://isi.edu/integration/karma/dev#classLink",
                    "rdfsLabel": null
                },
                "status": "ForcedByUser",
                "keyInfo": "UriOfInstance",
                "modelIds": null
            },
            {
                "id": "http://www.cidoc-crm.org/cidoc-crm/E22_Man-Made_Object1---http://isi.edu/integration/karma/dev#classLink---HN79843",
                "weight": 0.01,
                "type": "ClassInstanceLink",
                "label": {
                    "uri": "http://isi.edu/integration/karma/dev#classLink",
                    "rdfsLabel": null
                },
                "status": "ForcedByUser",
                "keyInfo": "UriOfInstance",
                "modelIds": null
            },
            {
                "id": "http://www.cidoc-crm.org/cidoc-crm/E57_Material1---http://www.w3.org/2004/02/skos/core#broadMatch---HN87348",
                "weight": 0.01,
                "type": "DataPropertyLink",
                "label": {
                    "uri": "http://www.w3.org/2004/02/skos/core#broadMatch",
                    "rdfsLabel": "has broader match"
                },
                "status": "ForcedByUser",
                "keyInfo": "None",
                "modelIds": null
            },
            {
                "id": "http://www.cidoc-crm.org/cidoc-crm/E52_Time-Span1---http://www.cidoc-crm.org/cidoc-crm/P82a_begin_of_the_begin---HN47525",
                "weight": 0.01,
                "type": "DataPropertyLink",
                "label": {
                    "uri": "http://www.cidoc-crm.org/cidoc-crm/P82a_begin_of_the_begin",
                    "rdfsLabel": "begin of the begin"
                },
                "status": "ForcedByUser",
                "keyInfo": "None",
                "modelIds": null
            },
            {
                "id": "http://www.cidoc-crm.org/cidoc-crm/E33_Linguistic_Object2---http://www.w3.org/1999/02/22-rdf-syntax-ns#value---HN47544",
                "weight": 0.01,
                "type": "DataPropertyLink",
                "label": {
                    "uri": "http://www.w3.org/1999/02/22-rdf-syntax-ns#value",
                    "rdfsLabel": null
                },
                "status": "ForcedByUser",
                "keyInfo": "None",
                "modelIds": null
            },
            {
                "id": "http://www.cidoc-crm.org/cidoc-crm/E40_Legal_Body1---http://www.w3.org/2000/01/rdf-schema#label---HN94050",
                "weight": 0.01,
                "type": "DataPropertyLink",
                "label": {
                    "uri": "http://www.w3.org/2000/01/rdf-schema#label",
                    "rdfsLabel": null
                },
                "status": "ForcedByUser",
                "keyInfo": "None",
                "modelIds": null
            },
            {
                "id": "http://www.cidoc-crm.org/cidoc-crm/E33_Linguistic_Object3---http://www.w3.org/1999/02/22-rdf-syntax-ns#value---HN47569",
                "weight": 0.01,
                "type": "DataPropertyLink",
                "label": {
                    "uri": "http://www.w3.org/1999/02/22-rdf-syntax-ns#value",
                    "rdfsLabel": null
                },
                "status": "ForcedByUser",
                "keyInfo": "None",
                "modelIds": null
            },
            {
                "id": "http://www.cidoc-crm.org/cidoc-crm/E55_Type1---http://isi.edu/integration/karma/dev#classLink---HN80647",
                "weight": 0.01,
                "type": "ClassInstanceLink",
                "label": {
                    "uri": "http://isi.edu/integration/karma/dev#classLink",
                    "rdfsLabel": null
                },
                "status": "ForcedByUser",
                "keyInfo": "UriOfInstance",
                "modelIds": null
            },
            {
                "id": "http://xmlns.com/foaf/0.1/Document1---http://isi.edu/integration/karma/dev#classLink---HN90027",
                "weight": 0.01,
                "type": "ClassInstanceLink",
                "label": {
                    "uri": "http://isi.edu/integration/karma/dev#classLink",
                    "rdfsLabel": null
                },
                "status": "ForcedByUser",
                "keyInfo": "UriOfInstance",
                "modelIds": null
            },
            {
                "id": "http://www.cidoc-crm.org/cidoc-crm/E52_Time-Span1---http://www.cidoc-crm.org/cidoc-crm/P82b_end_of_the_end---HN47527",
                "weight": 0.01,
                "type": "DataPropertyLink",
                "label": {
                    "uri": "http://www.cidoc-crm.org/cidoc-crm/P82b_end_of_the_end",
                    "rdfsLabel": "end of the end"
                },
                "status": "ForcedByUser",
                "keyInfo": "None",
                "modelIds": null
            },
            {
                "id": "http://www.cidoc-crm.org/cidoc-crm/E52_Time-Span1---http://www.w3.org/2000/01/rdf-schema#label---HN47529",
                "weight": 0.01,
                "type": "DataPropertyLink",
                "label": {
                    "uri": "http://www.w3.org/2000/01/rdf-schema#label",
                    "rdfsLabel": null
                },
                "status": "ForcedByUser",
                "keyInfo": "None",
                "modelIds": null
            },
            {
                "id": "http://www.cidoc-crm.org/cidoc-crm/E52_Time-Span1---http://isi.edu/integration/karma/dev#classLink---HN83865",
                "weight": 0.01,
                "type": "ClassInstanceLink",
                "label": {
                    "uri": "http://isi.edu/integration/karma/dev#classLink",
                    "rdfsLabel": null
                },
                "status": "ForcedByUser",
                "keyInfo": "UriOfInstance",
                "modelIds": null
            },
            {
                "id": "http://www.cidoc-crm.org/cidoc-crm/E40_Legal_Body1---http://isi.edu/integration/karma/dev#classLink---HN90833",
                "weight": 0.01,
                "type": "ClassInstanceLink",
                "label": {
                    "uri": "http://isi.edu/integration/karma/dev#classLink",
                    "rdfsLabel": null
                },
                "status": "ForcedByUser",
                "keyInfo": "UriOfInstance",
                "modelIds": null
            },
            {
                "id": "http://www.cidoc-crm.org/cidoc-crm/E40_Legal_Body1---http://www.w3.org/2004/02/skos/core#exactMatch---http://vocab.getty.edu/ulan/5002791101",
                "weight": 0.01,
                "type": "ObjectPropertyLink",
                "label": {
                    "uri": "http://www.w3.org/2004/02/skos/core#exactMatch",
                    "rdfsLabel": "has exact match"
                },
                "objectPropertyType": "WithoutDomainAndRange",
                "status": "ForcedByUser",
                "keyInfo": "None",
                "modelIds": null
            },
            {
                "id": "http://www.cidoc-crm.org/cidoc-crm/E33_Linguistic_Object3---http://www.cidoc-crm.org/cidoc-crm/P2_has_type---http://vocab.getty.edu/aat/3004046701",
                "weight": 0.01,
                "type": "ObjectPropertyLink",
                "label": {
                    "uri": "http://www.cidoc-crm.org/cidoc-crm/P2_has_type",
                    "rdfsLabel": "has type"
                },
                "objectPropertyType": "None",
                "status": "ForcedByUser",
                "keyInfo": "None",
                "modelIds": null
            },
            {
                "id": "http://www.cidoc-crm.org/cidoc-crm/E22_Man-Made_Object1---http://www.cidoc-crm.org/cidoc-crm/P129i_is_subject_of---http://www.cidoc-crm.org/cidoc-crm/E33_Linguistic_Object2",
                "weight": 0.01,
                "type": "ObjectPropertyLink",
                "label": {
                    "uri": "http://www.cidoc-crm.org/cidoc-crm/P129i_is_subject_of",
                    "rdfsLabel": "is subject of"
                },
                "objectPropertyType": "Indirect",
                "status": "ForcedByUser",
                "keyInfo": "None",
                "modelIds": null
            },
            {
                "id": "http://www.cidoc-crm.org/cidoc-crm/E33_Linguistic_Object2---http://www.cidoc-crm.org/cidoc-crm/P2_has_type---http://vocab.getty.edu/aat/3002642371",
                "weight": 0.01,
                "type": "ObjectPropertyLink",
                "label": {
                    "uri": "http://www.cidoc-crm.org/cidoc-crm/P2_has_type",
                    "rdfsLabel": "has type"
                },
                "objectPropertyType": "None",
                "status": "ForcedByUser",
                "keyInfo": "None",
                "modelIds": null
            },
            {
                "id": "http://www.cidoc-crm.org/cidoc-crm/E42_Identifier1---http://www.cidoc-crm.org/cidoc-crm/P2_has_type---http://vocab.getty.edu/aat/3004046702",
                "weight": 0.01,
                "type": "ObjectPropertyLink",
                "label": {
                    "uri": "http://www.cidoc-crm.org/cidoc-crm/P2_has_type",
                    "rdfsLabel": "has type"
                },
                "objectPropertyType": "None",
                "status": "ForcedByUser",
                "keyInfo": "None",
                "modelIds": null
            },
            {
                "id": "http://www.cidoc-crm.org/cidoc-crm/E33_Linguistic_Object1---http://www.cidoc-crm.org/cidoc-crm/P2_has_type---http://vocab.getty.edu/aat/3000266871",
                "weight": 0.01,
                "type": "ObjectPropertyLink",
                "label": {
                    "uri": "http://www.cidoc-crm.org/cidoc-crm/P2_has_type",
                    "rdfsLabel": "has type"
                },
                "objectPropertyType": "None",
                "status": "ForcedByUser",
                "keyInfo": "None",
                "modelIds": null
            },
            {
                "id": "http://www.cidoc-crm.org/cidoc-crm/E17_Type_Assignment1---http://www.cidoc-crm.org/cidoc-crm/P21_had_general_purpose---http://vocab.getty.edu/aat/3001798691",
                "weight": 0.01,
                "type": "ObjectPropertyLink",
                "label": {
                    "uri": "http://www.cidoc-crm.org/cidoc-crm/P21_had_general_purpose",
                    "rdfsLabel": "had general purpose"
                },
                "objectPropertyType": "None",
                "status": "ForcedByUser",
                "keyInfo": "None",
                "modelIds": null
            },
            {
                "id": "http://www.cidoc-crm.org/cidoc-crm/E33_Linguistic_Object3---http://www.cidoc-crm.org/cidoc-crm/P2_has_type---http://vocab.getty.edu/aat/3000800911",
                "weight": 0.01,
                "type": "ObjectPropertyLink",
                "label": {
                    "uri": "http://www.cidoc-crm.org/cidoc-crm/P2_has_type",
                    "rdfsLabel": "has type"
                },
                "objectPropertyType": "None",
                "status": "ForcedByUser",
                "keyInfo": "None",
                "modelIds": null
            },
            {
                "id": "http://www.cidoc-crm.org/cidoc-crm/E22_Man-Made_Object1---http://www.cidoc-crm.org/cidoc-crm/P2_has_type---http://www.cidoc-crm.org/cidoc-crm/E55_Type1",
                "weight": 0.009999999776482582,
                "type": "ObjectPropertyLink",
                "label": {
                    "uri": "http://www.cidoc-crm.org/cidoc-crm/P2_has_type",
                    "rdfsLabel": "has type"
                },
                "objectPropertyType": "Indirect",
                "status": "ForcedByUser",
                "keyInfo": "None",
                "modelIds": null
            },
            {
                "id": "http://www.cidoc-crm.org/cidoc-crm/E42_Identifier2---http://www.cidoc-crm.org/cidoc-crm/P2_has_type---http://vocab.getty.edu/aat/3004046211",
                "weight": 0.01,
                "type": "ObjectPropertyLink",
                "label": {
                    "uri": "http://www.cidoc-crm.org/cidoc-crm/P2_has_type",
                    "rdfsLabel": "has type"
                },
                "objectPropertyType": "None",
                "status": "ForcedByUser",
                "keyInfo": "None",
                "modelIds": null
            }
        ]
    }
}