{
    "id": "wam_metadata.json",
    "name": "wam_metadata.json",
    "description": null,
    "sourceColumns": [
        {
            "id": "HN415",
            "hNodeId": "HN415",
            "columnName": "Homepage"
        },
        {
            "id": "HN413",
            "hNodeId": "HN413",
            "columnName": "Entities"
        },
        {
            "id": "HN435",
            "hNodeId": "HN435",
            "columnName": "Created"
        },
        {
            "id": "HN479",
            "hNodeId": "HN479",
            "columnName": "Sparql_endpoint"
        },
        {
            "id": "HN458",
            "hNodeId": "HN458",
            "columnName": "Classes"
        },
        {
            "id": "HN419",
            "hNodeId": "HN419",
            "columnName": "Description"
        },
        {
            "id": "HN417",
            "hNodeId": "HN417",
            "columnName": "Triples"
        },
        {
            "id": "HN411",
            "hNodeId": "HN411",
            "columnName": "Technical_feature"
        },
        {
            "id": "HN433",
            "hNodeId": "HN433",
            "columnName": "License"
        },
        {
            "id": "HN477",
            "hNodeId": "HN477",
            "columnName": "Issued"
        },
        {
            "id": "HN456",
            "hNodeId": "HN456",
            "columnName": "Modified"
        },
        {
            "id": "HN431",
            "hNodeId": "HN431",
            "columnName": "Publisher"
        },
        {
            "id": "HN470",
            "hNodeId": "HN470",
            "columnName": "values"
        },
        {
            "id": "HN427",
            "hNodeId": "HN427",
            "columnName": "Date"
        },
        {
            "id": "HN425",
            "hNodeId": "HN425",
            "columnName": "Example_resource"
        },
        {
            "id": "HN429",
            "hNodeId": "HN429",
            "columnName": "Properties"
        },
        {
            "id": "HN462",
            "hNodeId": "HN462",
            "columnName": "URI_pattern"
        },
        {
            "id": "HN441",
            "hNodeId": "HN441",
            "columnName": "values"
        },
        {
            "id": "HN460",
            "hNodeId": "HN460",
            "columnName": "Dataset_URI"
        },
        {
            "id": "HN483",
            "hNodeId": "HN483",
            "columnName": "Subject"
        },
        {
            "id": "HN423",
            "hNodeId": "HN423",
            "columnName": "RDF_data_dump"
        },
        {
            "id": "HN464",
            "hNodeId": "HN464",
            "columnName": "Creator"
        },
        {
            "id": "HN421",
            "hNodeId": "HN421",
            "columnName": "Title"
        },
        {
            "id": "HN487",
            "hNodeId": "HN487",
            "columnName": "HomepageURL"
        },
        {
            "id": "HN481",
            "hNodeId": "HN481",
            "columnName": "Contributor"
        }
    ],
    "mappingToSourceColumns": [
        {
            "id": "HN415",
            "sourceColumnId": "HN415"
        },
        {
            "id": "HN413",
            "sourceColumnId": "HN413"
        },
        {
            "id": "HN435",
            "sourceColumnId": "HN435"
        },
        {
            "id": "HN479",
            "sourceColumnId": "HN479"
        },
        {
            "id": "HN458",
            "sourceColumnId": "HN458"
        },
        {
            "id": "HN419",
            "sourceColumnId": "HN419"
        },
        {
            "id": "HN417",
            "sourceColumnId": "HN417"
        },
        {
            "id": "HN411",
            "sourceColumnId": "HN411"
        },
        {
            "id": "HN433",
            "sourceColumnId": "HN433"
        },
        {
            "id": "HN477",
            "sourceColumnId": "HN477"
        },
        {
            "id": "HN456",
            "sourceColumnId": "HN456"
        },
        {
            "id": "HN431",
            "sourceColumnId": "HN431"
        },
        {
            "id": "HN470",
            "sourceColumnId": "HN470"
        },
        {
            "id": "HN427",
            "sourceColumnId": "HN427"
        },
        {
            "id": "HN425",
            "sourceColumnId": "HN425"
        },
        {
            "id": "HN429",
            "sourceColumnId": "HN429"
        },
        {
            "id": "HN462",
            "sourceColumnId": "HN462"
        },
        {
            "id": "HN441",
            "sourceColumnId": "HN441"
        },
        {
            "id": "HN460",
            "sourceColumnId": "HN460"
        },
        {
            "id": "HN483",
            "sourceColumnId": "HN483"
        },
        {
            "id": "HN423",
            "sourceColumnId": "HN423"
        },
        {
            "id": "HN464",
            "sourceColumnId": "HN464"
        },
        {
            "id": "HN421",
            "sourceColumnId": "HN421"
        },
        {
            "id": "HN487",
            "sourceColumnId": "HN487"
        },
        {
            "id": "HN481",
            "sourceColumnId": "HN481"
        }
    ],
    "graph": {
        "nodes": [
            {
                "id": "http://rdfs.org/ns/void#Dataset1",
                "label": {
                    "uri": "http://rdfs.org/ns/void#Dataset",
                    "rdfsLabel": null
                },
                "type": "InternalNode",
                "modelIds": null
            },
            {
                "id": "http://xmlns.com/foaf/0.1/Document1",
                "label": {
                    "uri": "http://xmlns.com/foaf/0.1/Document",
                    "rdfsLabel": null
                },
                "type": "InternalNode",
                "modelIds": null
            },
            {
                "id": "HN415",
                "label": {
                    "uri": "HN415",
                    "rdfsLabel": null
                },
                "type": "ColumnNode",
                "hNodeId": "HN415",
                "columnName": "Homepage",
                "rdfLiteralType": null,
                "language": "",
                "userSemanticTypes": [
                    {
                        "hNodeId": "HN415",
                        "domain": {
                            "uri": "http://xmlns.com/foaf/0.1/Document",
                            "rdfsLabel": null
                        },
                        "type": {
                            "uri": "http://isi.edu/integration/karma/dev#classLink",
                            "rdfsLabel": null
                        },
                        "origin": "User",
                        "confidenceScore": 1.0
                    },
                    {
                        "hNodeId": "HN415",
                        "domain": {
                            "uri": "http://xmlns.com/foaf/0.1/Document",
                            "rdfsLabel": null
                        },
                        "type": {
                            "uri": "http://isi.edu/integration/karma/dev#classLink",
                            "rdfsLabel": null
                        },
                        "origin": "User",
                        "confidenceScore": 1.0
                    }
                ],
                "learnedSemanticTypes": null,
                "modelIds": null
            },
            {
                "id": "HN413",
                "label": {
                    "uri": "HN413",
                    "rdfsLabel": null
                },
                "type": "ColumnNode",
                "hNodeId": "HN413",
                "columnName": "Entities",
                "rdfLiteralType": null,
                "language": "",
                "userSemanticTypes": [
                    {
                        "hNodeId": "HN413",
                        "domain": {
                            "uri": "http://rdfs.org/ns/void#Dataset",
                            "rdfsLabel": null
                        },
                        "type": {
                            "uri": "http://rdfs.org/ns/void#entities",
                            "rdfsLabel": "number of entities"
                        },
                        "origin": "User",
                        "confidenceScore": 1.0
                    },
                    {
                        "hNodeId": "HN413",
                        "domain": {
                            "uri": "http://rdfs.org/ns/void#Dataset",
                            "rdfsLabel": null
                        },
                        "type": {
                            "uri": "http://rdfs.org/ns/void#entities",
                            "rdfsLabel": "number of entities"
                        },
                        "origin": "User",
                        "confidenceScore": 1.0
                    }
                ],
                "learnedSemanticTypes": null,
                "modelIds": null
            },
            {
                "id": "HN435",
                "label": {
                    "uri": "HN435",
                    "rdfsLabel": null
                },
                "type": "ColumnNode",
                "hNodeId": "HN435",
                "columnName": "Created",
                "rdfLiteralType": {
                    "uri": "http://www.w3.org/2001/XMLSchema#date",
                    "rdfsLabel": null
                },
                "language": "",
                "userSemanticTypes": [
                    {
                        "hNodeId": "HN435",
                        "domain": {
                            "uri": "http://rdfs.org/ns/void#Dataset",
                            "rdfsLabel": null
                        },
                        "type": {
                            "uri": "http://purl.org/dc/terms/created",
                            "rdfsLabel": "Date Created"
                        },
                        "origin": "User",
                        "confidenceScore": 1.0
                    },
                    {
                        "hNodeId": "HN435",
                        "domain": {
                            "uri": "http://rdfs.org/ns/void#Dataset",
                            "rdfsLabel": null
                        },
                        "type": {
                            "uri": "http://purl.org/dc/terms/created",
                            "rdfsLabel": "Date Created"
                        },
                        "origin": "User",
                        "confidenceScore": 1.0
                    }
                ],
                "learnedSemanticTypes": null,
                "modelIds": null
            },
            {
                "id": "HN479",
                "label": {
                    "uri": "HN479",
                    "rdfsLabel": null
                },
                "type": "ColumnNode",
                "hNodeId": "HN479",
                "columnName": "Sparql_endpoint",
                "rdfLiteralType": null,
                "language": "",
                "userSemanticTypes": [
                    {
                        "hNodeId": "HN479",
                        "domain": {
                            "uri": "http://rdfs.org/ns/void#Dataset",
                            "rdfsLabel": null
                        },
                        "type": {
                            "uri": "http://rdfs.org/ns/void#sparqlEndpoint",
                            "rdfsLabel": "has a SPARQL endpoint at"
                        },
                        "origin": "User",
                        "confidenceScore": 1.0
                    },
                    {
                        "hNodeId": "HN479",
                        "domain": {
                            "uri": "http://rdfs.org/ns/void#Dataset",
                            "rdfsLabel": null
                        },
                        "type": {
                            "uri": "http://rdfs.org/ns/void#sparqlEndpoint",
                            "rdfsLabel": "has a SPARQL endpoint at"
                        },
                        "origin": "User",
                        "confidenceScore": 1.0
                    }
                ],
                "learnedSemanticTypes": null,
                "modelIds": null
            },
            {
                "id": "HN458",
                "label": {
                    "uri": "HN458",
                    "rdfsLabel": null
                },
                "type": "ColumnNode",
                "hNodeId": "HN458",
                "columnName": "Classes",
                "rdfLiteralType": null,
                "language": "",
                "userSemanticTypes": [
                    {
                        "hNodeId": "HN458",
                        "domain": {
                            "uri": "http://rdfs.org/ns/void#Dataset",
                            "rdfsLabel": null
                        },
                        "type": {
                            "uri": "http://rdfs.org/ns/void#classes",
                            "rdfsLabel": "classes"
                        },
                        "origin": "User",
                        "confidenceScore": 1.0
                    },
                    {
                        "hNodeId": "HN458",
                        "domain": {
                            "uri": "http://rdfs.org/ns/void#Dataset",
                            "rdfsLabel": null
                        },
                        "type": {
                            "uri": "http://rdfs.org/ns/void#classes",
                            "rdfsLabel": "classes"
                        },
                        "origin": "User",
                        "confidenceScore": 1.0
                    }
                ],
                "learnedSemanticTypes": null,
                "modelIds": null
            },
            {
                "id": "HN419",
                "label": {
                    "uri": "HN419",
                    "rdfsLabel": null
                },
                "type": "ColumnNode",
                "hNodeId": "HN419",
                "columnName": "Description",
                "rdfLiteralType": null,
                "language": "",
                "userSemanticTypes": [
                    {
                        "hNodeId": "HN419",
                        "domain": {
                            "uri": "http://rdfs.org/ns/void#Dataset",
                            "rdfsLabel": null
                        },
                        "type": {
                            "uri": "http://purl.org/dc/terms/description",
                            "rdfsLabel": "Description"
                        },
                        "origin": "User",
                        "confidenceScore": 1.0
                    },
                    {
                        "hNodeId": "HN419",
                        "domain": {
                            "uri": "http://rdfs.org/ns/void#Dataset",
                            "rdfsLabel": null
                        },
                        "type": {
                            "uri": "http://purl.org/dc/terms/description",
                            "rdfsLabel": "Description"
                        },
                        "origin": "User",
                        "confidenceScore": 1.0
                    }
                ],
                "learnedSemanticTypes": null,
                "modelIds": null
            },
            {
                "id": "HN417",
                "label": {
                    "uri": "HN417",
                    "rdfsLabel": null
                },
                "type": "ColumnNode",
                "hNodeId": "HN417",
                "columnName": "Triples",
                "rdfLiteralType": null,
                "language": "",
                "userSemanticTypes": [
                    {
                        "hNodeId": "HN417",
                        "domain": {
                            "uri": "http://rdfs.org/ns/void#Dataset",
                            "rdfsLabel": null
                        },
                        "type": {
                            "uri": "http://rdfs.org/ns/void#triples",
                            "rdfsLabel": "number of triples"
                        },
                        "origin": "User",
                        "confidenceScore": 1.0
                    },
                    {
                        "hNodeId": "HN417",
                        "domain": {
                            "uri": "http://rdfs.org/ns/void#Dataset",
                            "rdfsLabel": null
                        },
                        "type": {
                            "uri": "http://rdfs.org/ns/void#triples",
                            "rdfsLabel": "number of triples"
                        },
                        "origin": "User",
                        "confidenceScore": 1.0
                    }
                ],
                "learnedSemanticTypes": null,
                "modelIds": null
            },
            {
                "id": "HN411",
                "label": {
                    "uri": "HN411",
                    "rdfsLabel": null
                },
                "type": "ColumnNode",
                "hNodeId": "HN411",
                "columnName": "Technical_feature",
                "rdfLiteralType": null,
                "language": "",
                "userSemanticTypes": [
                    {
                        "hNodeId": "HN411",
                        "domain": {
                            "uri": "http://rdfs.org/ns/void#Dataset",
                            "rdfsLabel": null
                        },
                        "type": {
                            "uri": "http://rdfs.org/ns/void#feature",
                            "rdfsLabel": "feature"
                        },
                        "origin": "User",
                        "confidenceScore": 1.0
                    },
                    {
                        "hNodeId": "HN411",
                        "domain": {
                            "uri": "http://rdfs.org/ns/void#Dataset",
                            "rdfsLabel": null
                        },
                        "type": {
                            "uri": "http://rdfs.org/ns/void#feature",
                            "rdfsLabel": "feature"
                        },
                        "origin": "User",
                        "confidenceScore": 1.0
                    }
                ],
                "learnedSemanticTypes": null,
                "modelIds": null
            },
            {
                "id": "HN433",
                "label": {
                    "uri": "HN433",
                    "rdfsLabel": null
                },
                "type": "ColumnNode",
                "hNodeId": "HN433",
                "columnName": "License",
                "rdfLiteralType": null,
                "language": "",
                "userSemanticTypes": [
                    {
                        "hNodeId": "HN433",
                        "domain": {
                            "uri": "http://rdfs.org/ns/void#Dataset",
                            "rdfsLabel": null
                        },
                        "type": {
                            "uri": "http://purl.org/dc/terms/license",
                            "rdfsLabel": "License"
                        },
                        "origin": "User",
                        "confidenceScore": 1.0
                    },
                    {
                        "hNodeId": "HN433",
                        "domain": {
                            "uri": "http://rdfs.org/ns/void#Dataset",
                            "rdfsLabel": null
                        },
                        "type": {
                            "uri": "http://purl.org/dc/terms/license",
                            "rdfsLabel": "License"
                        },
                        "origin": "User",
                        "confidenceScore": 1.0
                    }
                ],
                "learnedSemanticTypes": null,
                "modelIds": null
            },
            {
                "id": "HN477",
                "label": {
                    "uri": "HN477",
                    "rdfsLabel": null
                },
                "type": "ColumnNode",
                "hNodeId": "HN477",
                "columnName": "Issued",
                "rdfLiteralType": {
                    "uri": "http://www.w3.org/2001/XMLSchema#date",
                    "rdfsLabel": null
                },
                "language": "",
                "userSemanticTypes": [
                    {
                        "hNodeId": "HN477",
                        "domain": {
                            "uri": "http://rdfs.org/ns/void#Dataset",
                            "rdfsLabel": null
                        },
                        "type": {
                            "uri": "http://purl.org/dc/terms/issued",
                            "rdfsLabel": "Date Issued"
                        },
                        "origin": "User",
                        "confidenceScore": 1.0
                    },
                    {
                        "hNodeId": "HN477",
                        "domain": {
                            "uri": "http://rdfs.org/ns/void#Dataset",
                            "rdfsLabel": null
                        },
                        "type": {
                            "uri": "http://purl.org/dc/terms/issued",
                            "rdfsLabel": "Date Issued"
                        },
                        "origin": "User",
                        "confidenceScore": 1.0
                    }
                ],
                "learnedSemanticTypes": null,
                "modelIds": null
            },
            {
                "id": "HN456",
                "label": {
                    "uri": "HN456",
                    "rdfsLabel": null
                },
                "type": "ColumnNode",
                "hNodeId": "HN456",
                "columnName": "Modified",
                "rdfLiteralType": {
                    "uri": "http://www.w3.org/2001/XMLSchema#date",
                    "rdfsLabel": null
                },
                "language": "",
                "userSemanticTypes": [
                    {
                        "hNodeId": "HN456",
                        "domain": {
                            "uri": "http://rdfs.org/ns/void#Dataset",
                            "rdfsLabel": null
                        },
                        "type": {
                            "uri": "http://purl.org/dc/terms/modified",
                            "rdfsLabel": "Date Modified"
                        },
                        "origin": "User",
                        "confidenceScore": 1.0
                    },
                    {
                        "hNodeId": "HN456",
                        "domain": {
                            "uri": "http://rdfs.org/ns/void#Dataset",
                            "rdfsLabel": null
                        },
                        "type": {
                            "uri": "http://purl.org/dc/terms/modified",
                            "rdfsLabel": "Date Modified"
                        },
                        "origin": "User",
                        "confidenceScore": 1.0
                    }
                ],
                "learnedSemanticTypes": null,
                "modelIds": null
            },
            {
                "id": "HN431",
                "label": {
                    "uri": "HN431",
                    "rdfsLabel": null
                },
                "type": "ColumnNode",
                "hNodeId": "HN431",
                "columnName": "Publisher",
                "rdfLiteralType": null,
                "language": "",
                "userSemanticTypes": [
                    {
                        "hNodeId": "HN431",
                        "domain": {
                            "uri": "http://rdfs.org/ns/void#Dataset",
                            "rdfsLabel": null
                        },
                        "type": {
                            "uri": "http://purl.org/dc/terms/publisher",
                            "rdfsLabel": "Publisher"
                        },
                        "origin": "User",
                        "confidenceScore": 1.0
                    },
                    {
                        "hNodeId": "HN431",
                        "domain": {
                            "uri": "http://rdfs.org/ns/void#Dataset",
                            "rdfsLabel": null
                        },
                        "type": {
                            "uri": "http://purl.org/dc/terms/publisher",
                            "rdfsLabel": "Publisher"
                        },
                        "origin": "User",
                        "confidenceScore": 1.0
                    }
                ],
                "learnedSemanticTypes": null,
                "modelIds": null
            },
            {
                "id": "HN470",
                "label": {
                    "uri": "HN470",
                    "rdfsLabel": null
                },
                "type": "ColumnNode",
                "hNodeId": "HN470",
                "columnName": "values",
                "rdfLiteralType": null,
                "language": "",
                "userSemanticTypes": [
                    {
                        "hNodeId": "HN470",
                        "domain": {
                            "uri": "http://rdfs.org/ns/void#Dataset",
                            "rdfsLabel": null
                        },
                        "type": {
                            "uri": "http://purl.org/dc/terms/source",
                            "rdfsLabel": "Source"
                        },
                        "origin": "User",
                        "confidenceScore": 1.0
                    },
                    {
                        "hNodeId": "HN470",
                        "domain": {
                            "uri": "http://rdfs.org/ns/void#Dataset",
                            "rdfsLabel": null
                        },
                        "type": {
                            "uri": "http://purl.org/dc/terms/source",
                            "rdfsLabel": "Source"
                        },
                        "origin": "User",
                        "confidenceScore": 1.0
                    }
                ],
                "learnedSemanticTypes": null,
                "modelIds": null
            },
            {
                "id": "HN427",
                "label": {
                    "uri": "HN427",
                    "rdfsLabel": null
                },
                "type": "ColumnNode",
                "hNodeId": "HN427",
                "columnName": "Date",
                "rdfLiteralType": {
                    "uri": "http://www.w3.org/2001/XMLSchema#date",
                    "rdfsLabel": null
                },
                "language": "",
                "userSemanticTypes": [
                    {
                        "hNodeId": "HN427",
                        "domain": {
                            "uri": "http://rdfs.org/ns/void#Dataset",
                            "rdfsLabel": null
                        },
                        "type": {
                            "uri": "http://purl.org/dc/terms/date",
                            "rdfsLabel": "Date"
                        },
                        "origin": "User",
                        "confidenceScore": 1.0
                    },
                    {
                        "hNodeId": "HN427",
                        "domain": {
                            "uri": "http://rdfs.org/ns/void#Dataset",
                            "rdfsLabel": null
                        },
                        "type": {
                            "uri": "http://purl.org/dc/terms/date",
                            "rdfsLabel": "Date"
                        },
                        "origin": "User",
                        "confidenceScore": 1.0
                    }
                ],
                "learnedSemanticTypes": null,
                "modelIds": null
            },
            {
                "id": "HN425",
                "label": {
                    "uri": "HN425",
                    "rdfsLabel": null
                },
                "type": "ColumnNode",
                "hNodeId": "HN425",
                "columnName": "Example_resource",
                "rdfLiteralType": null,
                "language": "",
                "userSemanticTypes": [
                    {
                        "hNodeId": "HN425",
                        "domain": {
                            "uri": "http://rdfs.org/ns/void#Dataset",
                            "rdfsLabel": null
                        },
                        "type": {
                            "uri": "http://rdfs.org/ns/void#exampleResource",
                            "rdfsLabel": "example resource of dataset"
                        },
                        "origin": "User",
                        "confidenceScore": 1.0
                    },
                    {
                        "hNodeId": "HN425",
                        "domain": {
                            "uri": "http://rdfs.org/ns/void#Dataset",
                            "rdfsLabel": null
                        },
                        "type": {
                            "uri": "http://rdfs.org/ns/void#exampleResource",
                            "rdfsLabel": "example resource of dataset"
                        },
                        "origin": "User",
                        "confidenceScore": 1.0
                    }
                ],
                "learnedSemanticTypes": null,
                "modelIds": null
            },
            {
                "id": "HN429",
                "label": {
                    "uri": "HN429",
                    "rdfsLabel": null
                },
                "type": "ColumnNode",
                "hNodeId": "HN429",
                "columnName": "Properties",
                "rdfLiteralType": null,
                "language": "",
                "userSemanticTypes": [
                    {
                        "hNodeId": "HN429",
                        "domain": {
                            "uri": "http://rdfs.org/ns/void#Dataset",
                            "rdfsLabel": null
                        },
                        "type": {
                            "uri": "http://rdfs.org/ns/void#properties",
                            "rdfsLabel": "number of properties"
                        },
                        "origin": "User",
                        "confidenceScore": 1.0
                    },
                    {
                        "hNodeId": "HN429",
                        "domain": {
                            "uri": "http://rdfs.org/ns/void#Dataset",
                            "rdfsLabel": null
                        },
                        "type": {
                            "uri": "http://rdfs.org/ns/void#properties",
                            "rdfsLabel": "number of properties"
                        },
                        "origin": "User",
                        "confidenceScore": 1.0
                    }
                ],
                "learnedSemanticTypes": null,
                "modelIds": null
            },
            {
                "id": "HN462",
                "label": {
                    "uri": "HN462",
                    "rdfsLabel": null
                },
                "type": "ColumnNode",
                "hNodeId": "HN462",
                "columnName": "URI_pattern",
                "rdfLiteralType": null,
                "language": "",
                "userSemanticTypes": [
                    {
                        "hNodeId": "HN462",
                        "domain": {
                            "uri": "http://rdfs.org/ns/void#Dataset",
                            "rdfsLabel": null
                        },
                        "type": {
                            "uri": "http://rdfs.org/ns/void#uriSpace",
                            "rdfsLabel": "URI space"
                        },
                        "origin": "User",
                        "confidenceScore": 1.0
                    },
                    {
                        "hNodeId": "HN462",
                        "domain": {
                            "uri": "http://rdfs.org/ns/void#Dataset",
                            "rdfsLabel": null
                        },
                        "type": {
                            "uri": "http://rdfs.org/ns/void#uriSpace",
                            "rdfsLabel": "URI space"
                        },
                        "origin": "User",
                        "confidenceScore": 1.0
                    }
                ],
                "learnedSemanticTypes": null,
                "modelIds": null
            },
            {
                "id": "HN441",
                "label": {
                    "uri": "HN441",
                    "rdfsLabel": null
                },
                "type": "ColumnNode",
                "hNodeId": "HN441",
                "columnName": "values",
                "rdfLiteralType": null,
                "language": "",
                "userSemanticTypes": [
                    {
                        "hNodeId": "HN441",
                        "domain": {
                            "uri": "http://rdfs.org/ns/void#Dataset",
                            "rdfsLabel": null
                        },
                        "type": {
                            "uri": "http://rdfs.org/ns/void#vocabulary",
                            "rdfsLabel": "vocabulary"
                        },
                        "origin": "User",
                        "confidenceScore": 1.0
                    },
                    {
                        "hNodeId": "HN441",
                        "domain": {
                            "uri": "http://rdfs.org/ns/void#Dataset",
                            "rdfsLabel": null
                        },
                        "type": {
                            "uri": "http://rdfs.org/ns/void#vocabulary",
                            "rdfsLabel": "vocabulary"
                        },
                        "origin": "User",
                        "confidenceScore": 1.0
                    }
                ],
                "learnedSemanticTypes": null,
                "modelIds": null
            },
            {
                "id": "HN460",
                "label": {
                    "uri": "HN460",
                    "rdfsLabel": null
                },
                "type": "ColumnNode",
                "hNodeId": "HN460",
                "columnName": "Dataset_URI",
                "rdfLiteralType": null,
                "language": "",
                "userSemanticTypes": [
                    {
                        "hNodeId": "HN460",
                        "domain": {
                            "uri": "http://rdfs.org/ns/void#Dataset",
                            "rdfsLabel": null
                        },
                        "type": {
                            "uri": "http://isi.edu/integration/karma/dev#classLink",
                            "rdfsLabel": null
                        },
                        "origin": "User",
                        "confidenceScore": 1.0
                    },
                    {
                        "hNodeId": "HN460",
                        "domain": {
                            "uri": "http://rdfs.org/ns/void#Dataset",
                            "rdfsLabel": null
                        },
                        "type": {
                            "uri": "http://isi.edu/integration/karma/dev#classLink",
                            "rdfsLabel": null
                        },
                        "origin": "User",
                        "confidenceScore": 1.0
                    }
                ],
                "learnedSemanticTypes": null,
                "modelIds": null
            },
            {
                "id": "HN483",
                "label": {
                    "uri": "HN483",
                    "rdfsLabel": null
                },
                "type": "ColumnNode",
                "hNodeId": "HN483",
                "columnName": "Subject",
                "rdfLiteralType": null,
                "language": "",
                "userSemanticTypes": [
                    {
                        "hNodeId": "HN483",
                        "domain": {
                            "uri": "http://rdfs.org/ns/void#Dataset",
                            "rdfsLabel": null
                        },
                        "type": {
                            "uri": "http://purl.org/dc/terms/subject",
                            "rdfsLabel": "Subject"
                        },
                        "origin": "User",
                        "confidenceScore": 1.0
                    },
                    {
                        "hNodeId": "HN483",
                        "domain": {
                            "uri": "http://rdfs.org/ns/void#Dataset",
                            "rdfsLabel": null
                        },
                        "type": {
                            "uri": "http://purl.org/dc/terms/subject",
                            "rdfsLabel": "Subject"
                        },
                        "origin": "User",
                        "confidenceScore": 1.0
                    }
                ],
                "learnedSemanticTypes": null,
                "modelIds": null
            },
            {
                "id": "HN423",
                "label": {
                    "uri": "HN423",
                    "rdfsLabel": null
                },
                "type": "ColumnNode",
                "hNodeId": "HN423",
                "columnName": "RDF_data_dump",
                "rdfLiteralType": null,
                "language": "",
                "userSemanticTypes": [
                    {
                        "hNodeId": "HN423",
                        "domain": {
                            "uri": "http://rdfs.org/ns/void#Dataset",
                            "rdfsLabel": null
                        },
                        "type": {
                            "uri": "http://rdfs.org/ns/void#dataDump",
                            "rdfsLabel": "Data Dump"
                        },
                        "origin": "User",
                        "confidenceScore": 1.0
                    },
                    {
                        "hNodeId": "HN423",
                        "domain": {
                            "uri": "http://rdfs.org/ns/void#Dataset",
                            "rdfsLabel": null
                        },
                        "type": {
                            "uri": "http://rdfs.org/ns/void#dataDump",
                            "rdfsLabel": "Data Dump"
                        },
                        "origin": "User",
                        "confidenceScore": 1.0
                    }
                ],
                "learnedSemanticTypes": null,
                "modelIds": null
            },
            {
                "id": "HN464",
                "label": {
                    "uri": "HN464",
                    "rdfsLabel": null
                },
                "type": "ColumnNode",
                "hNodeId": "HN464",
                "columnName": "Creator",
                "rdfLiteralType": null,
                "language": "",
                "userSemanticTypes": [
                    {
                        "hNodeId": "HN464",
                        "domain": {
                            "uri": "http://rdfs.org/ns/void#Dataset",
                            "rdfsLabel": null
                        },
                        "type": {
                            "uri": "http://purl.org/dc/terms/creator",
                            "rdfsLabel": "Creator"
                        },
                        "origin": "User",
                        "confidenceScore": 1.0
                    },
                    {
                        "hNodeId": "HN464",
                        "domain": {
                            "uri": "http://rdfs.org/ns/void#Dataset",
                            "rdfsLabel": null
                        },
                        "type": {
                            "uri": "http://purl.org/dc/terms/creator",
                            "rdfsLabel": "Creator"
                        },
                        "origin": "User",
                        "confidenceScore": 1.0
                    }
                ],
                "learnedSemanticTypes": null,
                "modelIds": null
            },
            {
                "id": "HN421",
                "label": {
                    "uri": "HN421",
                    "rdfsLabel": null
                },
                "type": "ColumnNode",
                "hNodeId": "HN421",
                "columnName": "Title",
                "rdfLiteralType": null,
                "language": "",
                "userSemanticTypes": [
                    {
                        "hNodeId": "HN421",
                        "domain": {
                            "uri": "http://rdfs.org/ns/void#Dataset",
                            "rdfsLabel": null
                        },
                        "type": {
                            "uri": "http://purl.org/dc/terms/title",
                            "rdfsLabel": "Title"
                        },
                        "origin": "User",
                        "confidenceScore": 1.0
                    },
                    {
                        "hNodeId": "HN421",
                        "domain": {
                            "uri": "http://rdfs.org/ns/void#Dataset",
                            "rdfsLabel": null
                        },
                        "type": {
                            "uri": "http://purl.org/dc/terms/title",
                            "rdfsLabel": "Title"
                        },
                        "origin": "User",
                        "confidenceScore": 1.0
                    }
                ],
                "learnedSemanticTypes": null,
                "modelIds": null
            },
            {
                "id": "HN487",
                "label": {
                    "uri": "HN487",
                    "rdfsLabel": null
                },
                "type": "ColumnNode",
                "hNodeId": "HN487",
                "columnName": "HomepageURL",
                "rdfLiteralType": null,
                "language": "",
                "userSemanticTypes": [
                    {
                        "hNodeId": "HN487",
                        "domain": {
                            "uri": "http://xmlns.com/foaf/0.1/Document",
                            "rdfsLabel": null
                        },
                        "type": {
                            "uri": "http://www.w3.org/2000/01/rdf-schema#label",
                            "rdfsLabel": null
                        },
                        "origin": "User",
                        "confidenceScore": 1.0
                    },
                    {
                        "hNodeId": "HN487",
                        "domain": {
                            "uri": "http://xmlns.com/foaf/0.1/Document",
                            "rdfsLabel": null
                        },
                        "type": {
                            "uri": "http://www.w3.org/2000/01/rdf-schema#label",
                            "rdfsLabel": null
                        },
                        "origin": "User",
                        "confidenceScore": 1.0
                    }
                ],
                "learnedSemanticTypes": null,
                "modelIds": null
            },
            {
                "id": "HN481",
                "label": {
                    "uri": "HN481",
                    "rdfsLabel": null
                },
                "type": "ColumnNode",
                "hNodeId": "HN481",
                "columnName": "Contributor",
                "rdfLiteralType": null,
                "language": "",
                "userSemanticTypes": [
                    {
                        "hNodeId": "HN481",
                        "domain": {
                            "uri": "http://rdfs.org/ns/void#Dataset",
                            "rdfsLabel": null
                        },
                        "type": {
                            "uri": "http://purl.org/dc/terms/contributor",
                            "rdfsLabel": "Contributor"
                        },
                        "origin": "User",
                        "confidenceScore": 1.0
                    },
                    {
                        "hNodeId": "HN481",
                        "domain": {
                            "uri": "http://rdfs.org/ns/void#Dataset",
                            "rdfsLabel": null
                        },
                        "type": {
                            "uri": "http://purl.org/dc/terms/contributor",
                            "rdfsLabel": "Contributor"
                        },
                        "origin": "User",
                        "confidenceScore": 1.0
                    }
                ],
                "learnedSemanticTypes": null,
                "modelIds": null
            }
        ],
        "links": [
            {
                "id": "http://rdfs.org/ns/void#Dataset1---http://xmlns.com/foaf/0.1/homepage---http://xmlns.com/foaf/0.1/Document1",
                "weight": 0.009999999776482582,
                "type": "ObjectPropertyLink",
                "label": {
                    "uri": "http://xmlns.com/foaf/0.1/homepage",
                    "rdfsLabel": "homepage"
                },
                "objectPropertyType": "WithOnlyRange",
                "status": "ForcedByUser",
                "keyInfo": "None",
                "modelIds": null
            },
            {
                "id": "http://xmlns.com/foaf/0.1/Document1---http://isi.edu/integration/karma/dev#classLink---HN415",
                "weight": 0.01,
                "type": "ClassInstanceLink",
                "label": {
                    "uri": "http://isi.edu/integration/karma/dev#classLink",
                    "rdfsLabel": null
                },
                "status": "ForcedByUser",
                "keyInfo": "UriOfInstance",
                "modelIds": null
            },
            {
                "id": "http://rdfs.org/ns/void#Dataset1---http://rdfs.org/ns/void#entities---HN413",
                "weight": 0.01,
                "type": "DataPropertyLink",
                "label": {
                    "uri": "http://rdfs.org/ns/void#entities",
                    "rdfsLabel": "number of entities"
                },
                "status": "ForcedByUser",
                "keyInfo": "None",
                "modelIds": null
            },
            {
                "id": "http://rdfs.org/ns/void#Dataset1---http://purl.org/dc/terms/created---HN435",
                "weight": 0.01,
                "type": "DataPropertyLink",
                "label": {
                    "uri": "http://purl.org/dc/terms/created",
                    "rdfsLabel": "Date Created"
                },
                "status": "ForcedByUser",
                "keyInfo": "None",
                "modelIds": null
            },
            {
                "id": "http://rdfs.org/ns/void#Dataset1---http://rdfs.org/ns/void#sparqlEndpoint---HN479",
                "weight": 0.01,
                "type": "DataPropertyLink",
                "label": {
                    "uri": "http://rdfs.org/ns/void#sparqlEndpoint",
                    "rdfsLabel": "has a SPARQL endpoint at"
                },
                "status": "ForcedByUser",
                "keyInfo": "None",
                "modelIds": null
            },
            {
                "id": "http://rdfs.org/ns/void#Dataset1---http://rdfs.org/ns/void#classes---HN458",
                "weight": 0.01,
                "type": "DataPropertyLink",
                "label": {
                    "uri": "http://rdfs.org/ns/void#classes",
                    "rdfsLabel": "classes"
                },
                "status": "ForcedByUser",
                "keyInfo": "None",
                "modelIds": null
            },
            {
                "id": "http://rdfs.org/ns/void#Dataset1---http://purl.org/dc/terms/description---HN419",
                "weight": 0.01,
                "type": "DataPropertyLink",
                "label": {
                    "uri": "http://purl.org/dc/terms/description",
                    "rdfsLabel": "Description"
                },
                "status": "ForcedByUser",
                "keyInfo": "None",
                "modelIds": null
            },
            {
                "id": "http://rdfs.org/ns/void#Dataset1---http://rdfs.org/ns/void#triples---HN417",
                "weight": 0.01,
                "type": "DataPropertyLink",
                "label": {
                    "uri": "http://rdfs.org/ns/void#triples",
                    "rdfsLabel": "number of triples"
                },
                "status": "ForcedByUser",
                "keyInfo": "None",
                "modelIds": null
            },
            {
                "id": "http://rdfs.org/ns/void#Dataset1---http://rdfs.org/ns/void#feature---HN411",
                "weight": 0.01,
                "type": "DataPropertyLink",
                "label": {
                    "uri": "http://rdfs.org/ns/void#feature",
                    "rdfsLabel": "feature"
                },
                "status": "ForcedByUser",
                "keyInfo": "None",
                "modelIds": null
            },
            {
                "id": "http://rdfs.org/ns/void#Dataset1---http://purl.org/dc/terms/license---HN433",
                "weight": 0.01,
                "type": "DataPropertyLink",
                "label": {
                    "uri": "http://purl.org/dc/terms/license",
                    "rdfsLabel": "License"
                },
                "status": "ForcedByUser",
                "keyInfo": "None",
                "modelIds": null
            },
            {
                "id": "http://rdfs.org/ns/void#Dataset1---http://purl.org/dc/terms/issued---HN477",
                "weight": 0.01,
                "type": "DataPropertyLink",
                "label": {
                    "uri": "http://purl.org/dc/terms/issued",
                    "rdfsLabel": "Date Issued"
                },
                "status": "ForcedByUser",
                "keyInfo": "None",
                "modelIds": null
            },
            {
                "id": "http://rdfs.org/ns/void#Dataset1---http://purl.org/dc/terms/modified---HN456",
                "weight": 0.01,
                "type": "DataPropertyLink",
                "label": {
                    "uri": "http://purl.org/dc/terms/modified",
                    "rdfsLabel": "Date Modified"
                },
                "status": "ForcedByUser",
                "keyInfo": "None",
                "modelIds": null
            },
            {
                "id": "http://rdfs.org/ns/void#Dataset1---http://purl.org/dc/terms/publisher---HN431",
                "weight": 0.01,
                "type": "DataPropertyLink",
                "label": {
                    "uri": "http://purl.org/dc/terms/publisher",
                    "rdfsLabel": "Publisher"
                },
                "status": "ForcedByUser",
                "keyInfo": "None",
                "modelIds": null
            },
            {
                "id": "http://rdfs.org/ns/void#Dataset1---http://purl.org/dc/terms/source---HN470",
                "weight": 0.01,
                "type": "DataPropertyLink",
                "label": {
                    "uri": "http://purl.org/dc/terms/source",
                    "rdfsLabel": "Source"
                },
                "status": "ForcedByUser",
                "keyInfo": "None",
                "modelIds": null
            },
            {
                "id": "http://rdfs.org/ns/void#Dataset1---http://purl.org/dc/terms/date---HN427",
                "weight": 0.01,
                "type": "DataPropertyLink",
                "label": {
                    "uri": "http://purl.org/dc/terms/date",
                    "rdfsLabel": "Date"
                },
                "status": "ForcedByUser",
                "keyInfo": "None",
                "modelIds": null
            },
            {
                "id": "http://rdfs.org/ns/void#Dataset1---http://rdfs.org/ns/void#exampleResource---HN425",
                "weight": 0.01,
                "type": "DataPropertyLink",
                "label": {
                    "uri": "http://rdfs.org/ns/void#exampleResource",
                    "rdfsLabel": "example resource of dataset"
                },
                "status": "ForcedByUser",
                "keyInfo": "None",
                "modelIds": null
            },
            {
                "id": "http://rdfs.org/ns/void#Dataset1---http://rdfs.org/ns/void#properties---HN429",
                "weight": 0.01,
                "type": "DataPropertyLink",
                "label": {
                    "uri": "http://rdfs.org/ns/void#properties",
                    "rdfsLabel": "number of properties"
                },
                "status": "ForcedByUser",
                "keyInfo": "None",
                "modelIds": null
            },
            {
                "id": "http://rdfs.org/ns/void#Dataset1---http://rdfs.org/ns/void#uriSpace---HN462",
                "weight": 0.01,
                "type": "DataPropertyLink",
                "label": {
                    "uri": "http://rdfs.org/ns/void#uriSpace",
                    "rdfsLabel": "URI space"
                },
                "status": "ForcedByUser",
                "keyInfo": "None",
                "modelIds": null
            },
            {
                "id": "http://rdfs.org/ns/void#Dataset1---http://rdfs.org/ns/void#vocabulary---HN441",
                "weight": 0.01,
                "type": "DataPropertyLink",
                "label": {
                    "uri": "http://rdfs.org/ns/void#vocabulary",
                    "rdfsLabel": "vocabulary"
                },
                "status": "ForcedByUser",
                "keyInfo": "None",
                "modelIds": null
            },
            {
                "id": "http://rdfs.org/ns/void#Dataset1---http://isi.edu/integration/karma/dev#classLink---HN460",
                "weight": 0.01,
                "type": "ClassInstanceLink",
                "label": {
                    "uri": "http://isi.edu/integration/karma/dev#classLink",
                    "rdfsLabel": null
                },
                "status": "ForcedByUser",
                "keyInfo": "UriOfInstance",
                "modelIds": null
            },
            {
                "id": "http://rdfs.org/ns/void#Dataset1---http://purl.org/dc/terms/subject---HN483",
                "weight": 0.01,
                "type": "DataPropertyLink",
                "label": {
                    "uri": "http://purl.org/dc/terms/subject",
                    "rdfsLabel": "Subject"
                },
                "status": "ForcedByUser",
                "keyInfo": "None",
                "modelIds": null
            },
            {
                "id": "http://rdfs.org/ns/void#Dataset1---http://rdfs.org/ns/void#dataDump---HN423",
                "weight": 0.01,
                "type": "DataPropertyLink",
                "label": {
                    "uri": "http://rdfs.org/ns/void#dataDump",
                    "rdfsLabel": "Data Dump"
                },
                "status": "ForcedByUser",
                "keyInfo": "None",
                "modelIds": null
            },
            {
                "id": "http://rdfs.org/ns/void#Dataset1---http://purl.org/dc/terms/creator---HN464",
                "weight": 0.01,
                "type": "DataPropertyLink",
                "label": {
                    "uri": "http://purl.org/dc/terms/creator",
                    "rdfsLabel": "Creator"
                },
                "status": "ForcedByUser",
                "keyInfo": "None",
                "modelIds": null
            },
            {
                "id": "http://rdfs.org/ns/void#Dataset1---http://purl.org/dc/terms/title---HN421",
                "weight": 0.01,
                "type": "DataPropertyLink",
                "label": {
                    "uri": "http://purl.org/dc/terms/title",
                    "rdfsLabel": "Title"
                },
                "status": "ForcedByUser",
                "keyInfo": "None",
                "modelIds": null
            },
            {
                "id": "http://xmlns.com/foaf/0.1/Document1---http://www.w3.org/2000/01/rdf-schema#label---HN487",
                "weight": 0.01,
                "type": "DataPropertyLink",
                "label": {
                    "uri": "http://www.w3.org/2000/01/rdf-schema#label",
                    "rdfsLabel": null
                },
                "status": "ForcedByUser",
                "keyInfo": "None",
                "modelIds": null
            },
            {
                "id": "http://rdfs.org/ns/void#Dataset1---http://purl.org/dc/terms/contributor---HN481",
                "weight": 0.01,
                "type": "DataPropertyLink",
                "label": {
                    "uri": "http://purl.org/dc/terms/contributor",
                    "rdfsLabel": "Contributor"
                },
                "status": "ForcedByUser",
                "keyInfo": "None",
                "modelIds": null
            }
        ]
    }
}