{
    "id": "WAM_XMLExport_AAC_Geography.xml",
    "name": "WAM_XMLExport_AAC_Geography.xml",
    "description": null,
    "sourceColumns": [
        {
            "id": "HN19564",
            "hNodeId": "HN19564",
            "columnName": "LatitudeValue"
        },
        {
            "id": "HN21359",
            "hNodeId": "HN21359",
            "columnName": "LongitudeValue"
        },
        {
            "id": "HN37",
            "hNodeId": "HN37",
            "columnName": "GeographyTerm"
        },
        {
            "id": "HN18664",
            "hNodeId": "HN18664",
            "columnName": "LatitudeURI"
        },
        {
            "id": "HN16832",
            "hNodeId": "HN16832",
            "columnName": "ProductionURI"
        },
        {
            "id": "HN17743",
            "hNodeId": "HN17743",
            "columnName": "PlaceURI"
        },
        {
            "id": "HN16017",
            "hNodeId": "HN16017",
            "columnName": "ObjectURI"
        },
        {
            "id": "HN20461",
            "hNodeId": "HN20461",
            "columnName": "LongitudeURI"
        }
    ],
    "mappingToSourceColumns": [
        {
            "id": "HN19564",
            "sourceColumnId": "HN19564"
        },
        {
            "id": "HN21359",
            "sourceColumnId": "HN21359"
        },
        {
            "id": "HN37",
            "sourceColumnId": "HN37"
        },
        {
            "id": "HN16832",
            "sourceColumnId": "HN16832"
        },
        {
            "id": "HN18664",
            "sourceColumnId": "HN18664"
        },
        {
            "id": "HN17743",
            "sourceColumnId": "HN17743"
        },
        {
            "id": "HN16017",
            "sourceColumnId": "HN16017"
        },
        {
            "id": "HN20461",
            "sourceColumnId": "HN20461"
        }
    ],
    "graph": {
        "nodes": [
            {
                "id": "http://www.cidoc-crm.org/cidoc-crm/E12_Production1",
                "label": {
                    "uri": "http://www.cidoc-crm.org/cidoc-crm/E12_Production",
                    "rdfsLabel": null
                },
                "type": "InternalNode",
                "modelIds": null
            },
            {
                "id": "http://www.cidoc-crm.org/cidoc-crm/E53_Place1",
                "label": {
                    "uri": "http://www.cidoc-crm.org/cidoc-crm/E53_Place",
                    "rdfsLabel": null
                },
                "type": "InternalNode",
                "modelIds": null
            },
            {
                "id": "http://www.cidoc-crm.org/cidoc-crm/E22_Man-Made_Object1",
                "label": {
                    "uri": "http://www.cidoc-crm.org/cidoc-crm/E22_Man-Made_Object",
                    "rdfsLabel": null
                },
                "type": "InternalNode",
                "modelIds": null
            },
            {
                "id": "http://www.cidoc-crm.org/cidoc-crm/E47_Spatial_Coordinates1",
                "label": {
                    "uri": "http://www.cidoc-crm.org/cidoc-crm/E47_Spatial_Coordinates",
                    "rdfsLabel": null
                },
                "type": "InternalNode",
                "modelIds": null
            },
            {
                "id": "http://www.cidoc-crm.org/cidoc-crm/E47_Spatial_Coordinates2",
                "label": {
                    "uri": "http://www.cidoc-crm.org/cidoc-crm/E47_Spatial_Coordinates",
                    "rdfsLabel": null
                },
                "type": "InternalNode",
                "modelIds": null
            },
            {
                "id": "HN19564",
                "label": {
                    "uri": "HN19564",
                    "rdfsLabel": null
                },
                "type": "ColumnNode",
                "hNodeId": "HN19564",
                "columnName": "LatitudeValue",
                "rdfLiteralType": null,
                "language": "",
                "userSemanticTypes": [
                    {
                        "hNodeId": "HN19564",
                        "domain": {
                            "uri": "http://www.cidoc-crm.org/cidoc-crm/E47_Spatial_Coordinates",
                            "rdfsLabel": null
                        },
                        "type": {
                            "uri": "http://www.w3.org/1999/02/22-rdf-syntax-ns#value",
                            "rdfsLabel": null
                        },
                        "origin": "User",
                        "confidenceScore": 1.0
                    }
                ],
                "learnedSemanticTypes": [
                    {
                        "hNodeId": "HN19564",
                        "domain": {
                            "uri": "http://www.cidoc-crm.org/cidoc-crm/E47_Spatial_Coordinates",
                            "rdfsLabel": null
                        },
                        "type": {
                            "uri": "http://www.w3.org/1999/02/22-rdf-syntax-ns#value",
                            "rdfsLabel": null
                        },
                        "origin": "TfIdfModel",
                        "confidenceScore": 0.8068761978063292
                    },
                    {
                        "hNodeId": "HN19564",
                        "domain": {
                            "uri": "http://www.cidoc-crm.org/cidoc-crm/E82_Actor_Appellation",
                            "rdfsLabel": null
                        },
                        "type": {
                            "uri": "http://www.w3.org/1999/02/22-rdf-syntax-ns#value",
                            "rdfsLabel": null
                        },
                        "origin": "TfIdfModel",
                        "confidenceScore": 0.09317004027537208
                    },
                    {
                        "hNodeId": "HN19564",
                        "domain": {
                            "uri": "http://www.cidoc-crm.org/cidoc-crm/E39_Actor",
                            "rdfsLabel": null
                        },
                        "type": {
                            "uri": "http://www.w3.org/2000/01/rdf-schema#label",
                            "rdfsLabel": null
                        },
                        "origin": "TfIdfModel",
                        "confidenceScore": 0.08068761773016934
                    },
                    {
                        "hNodeId": "HN19564",
                        "domain": {
                            "uri": "http://www.cidoc-crm.org/cidoc-crm/E18_Physical_Thing",
                            "rdfsLabel": null
                        },
                        "type": {
                            "uri": "http://isi.edu/integration/karma/dev#classLink",
                            "rdfsLabel": null
                        },
                        "origin": "TfIdfModel",
                        "confidenceScore": 0.019266144188129334
                    }
                ],
                "modelIds": null
            },
            {
                "id": "HN21359",
                "label": {
                    "uri": "HN21359",
                    "rdfsLabel": null
                },
                "type": "ColumnNode",
                "hNodeId": "HN21359",
                "columnName": "LongitudeValue",
                "rdfLiteralType": null,
                "language": "",
                "userSemanticTypes": [
                    {
                        "hNodeId": "HN21359",
                        "domain": {
                            "uri": "http://www.cidoc-crm.org/cidoc-crm/E47_Spatial_Coordinates",
                            "rdfsLabel": null
                        },
                        "type": {
                            "uri": "http://www.w3.org/1999/02/22-rdf-syntax-ns#value",
                            "rdfsLabel": null
                        },
                        "origin": "User",
                        "confidenceScore": 1.0
                    }
                ],
                "learnedSemanticTypes": [
                    {
                        "hNodeId": "HN21359",
                        "domain": {
                            "uri": "http://www.cidoc-crm.org/cidoc-crm/E47_Spatial_Coordinates",
                            "rdfsLabel": null
                        },
                        "type": {
                            "uri": "http://www.w3.org/1999/02/22-rdf-syntax-ns#value",
                            "rdfsLabel": null
                        },
                        "origin": "TfIdfModel",
                        "confidenceScore": 0.7998620347756248
                    },
                    {
                        "hNodeId": "HN21359",
                        "domain": {
                            "uri": "http://www.cidoc-crm.org/cidoc-crm/E35_Title",
                            "rdfsLabel": null
                        },
                        "type": {
                            "uri": "http://www.w3.org/1999/02/22-rdf-syntax-ns#value",
                            "rdfsLabel": null
                        },
                        "origin": "TfIdfModel",
                        "confidenceScore": 0.11720757903199897
                    },
                    {
                        "hNodeId": "HN21359",
                        "domain": {
                            "uri": "http://www.cidoc-crm.org/cidoc-crm/E18_Physical_Thing",
                            "rdfsLabel": null
                        },
                        "type": {
                            "uri": "http://isi.edu/integration/karma/dev#classLink",
                            "rdfsLabel": null
                        },
                        "origin": "TfIdfModel",
                        "confidenceScore": 0.04607243634655669
                    },
                    {
                        "hNodeId": "HN21359",
                        "domain": {
                            "uri": "http://www.cidoc-crm.org/cidoc-crm/E54_Dimension",
                            "rdfsLabel": null
                        },
                        "type": {
                            "uri": "http://isi.edu/integration/karma/dev#classLink",
                            "rdfsLabel": null
                        },
                        "origin": "TfIdfModel",
                        "confidenceScore": 0.03685794984581959
                    }
                ],
                "modelIds": null
            },
            {
                "id": "HN37",
                "label": {
                    "uri": "HN37",
                    "rdfsLabel": null
                },
                "type": "ColumnNode",
                "hNodeId": "HN37",
                "columnName": "GeographyTerm",
                "rdfLiteralType": null,
                "language": "",
                "userSemanticTypes": [
                    {
                        "hNodeId": "HN37",
                        "domain": {
                            "uri": "http://www.cidoc-crm.org/cidoc-crm/E53_Place",
                            "rdfsLabel": null
                        },
                        "type": {
                            "uri": "http://www.w3.org/2000/01/rdf-schema#label",
                            "rdfsLabel": null
                        },
                        "origin": "User",
                        "confidenceScore": 1.0
                    }
                ],
                "learnedSemanticTypes": [
                    {
                        "hNodeId": "HN37",
                        "domain": {
                            "uri": "http://www.cidoc-crm.org/cidoc-crm/E33_Linguistic_Object",
                            "rdfsLabel": null
                        },
                        "type": {
                            "uri": "http://www.w3.org/1999/02/22-rdf-syntax-ns#value",
                            "rdfsLabel": null
                        },
                        "origin": "TfIdfModel",
                        "confidenceScore": 0.9923506176071608
                    },
                    {
                        "hNodeId": "HN37",
                        "domain": {
                            "uri": "http://www.cidoc-crm.org/cidoc-crm/E39_Actor",
                            "rdfsLabel": null
                        },
                        "type": {
                            "uri": "http://www.w3.org/2000/01/rdf-schema#label",
                            "rdfsLabel": null
                        },
                        "origin": "TfIdfModel",
                        "confidenceScore": 0.003701479047286378
                    },
                    {
                        "hNodeId": "HN37",
                        "domain": {
                            "uri": "http://www.cidoc-crm.org/cidoc-crm/E82_Actor_Appellation",
                            "rdfsLabel": null
                        },
                        "type": {
                            "uri": "http://www.w3.org/1999/02/22-rdf-syntax-ns#value",
                            "rdfsLabel": null
                        },
                        "origin": "TfIdfModel",
                        "confidenceScore": 0.002815108217441659
                    },
                    {
                        "hNodeId": "HN37",
                        "domain": {
                            "uri": "http://www.cidoc-crm.org/cidoc-crm/E22_Man-Made_Object",
                            "rdfsLabel": null
                        },
                        "type": {
                            "uri": "http://www.w3.org/2000/01/rdf-schema#label",
                            "rdfsLabel": null
                        },
                        "origin": "TfIdfModel",
                        "confidenceScore": 0.0011327951281111903
                    }
                ],
                "modelIds": null
            },
            {
                "id": "HN18664",
                "label": {
                    "uri": "HN18664",
                    "rdfsLabel": null
                },
                "type": "ColumnNode",
                "hNodeId": "HN18664",
                "columnName": "LatitudeURI",
                "rdfLiteralType": null,
                "language": "",
                "userSemanticTypes": [
                    {
                        "hNodeId": "HN18664",
                        "domain": {
                            "uri": "http://www.cidoc-crm.org/cidoc-crm/E47_Spatial_Coordinates",
                            "rdfsLabel": null
                        },
                        "type": {
                            "uri": "http://isi.edu/integration/karma/dev#classLink",
                            "rdfsLabel": null
                        },
                        "origin": "User",
                        "confidenceScore": 1.0
                    }
                ],
                "learnedSemanticTypes": [
                    {
                        "hNodeId": "HN18664",
                        "domain": {
                            "uri": "http://www.cidoc-crm.org/cidoc-crm/E53_Place",
                            "rdfsLabel": null
                        },
                        "type": {
                            "uri": "http://isi.edu/integration/karma/dev#classLink",
                            "rdfsLabel": null
                        },
                        "origin": "TfIdfModel",
                        "confidenceScore": 0.5624016735704742
                    },
                    {
                        "hNodeId": "HN18664",
                        "domain": {
                            "uri": "http://www.cidoc-crm.org/cidoc-crm/E12_Production",
                            "rdfsLabel": null
                        },
                        "type": {
                            "uri": "http://isi.edu/integration/karma/dev#classLink",
                            "rdfsLabel": null
                        },
                        "origin": "TfIdfModel",
                        "confidenceScore": 0.26023842882980436
                    },
                    {
                        "hNodeId": "HN18664",
                        "domain": {
                            "uri": "http://www.cidoc-crm.org/cidoc-crm/E52_Time-Span",
                            "rdfsLabel": null
                        },
                        "type": {
                            "uri": "http://isi.edu/integration/karma/dev#classLink",
                            "rdfsLabel": null
                        },
                        "origin": "TfIdfModel",
                        "confidenceScore": 0.1353616922180427
                    },
                    {
                        "hNodeId": "HN18664",
                        "domain": {
                            "uri": "http://www.cidoc-crm.org/cidoc-crm/E22_Man-Made_Object",
                            "rdfsLabel": null
                        },
                        "type": {
                            "uri": "http://isi.edu/integration/karma/dev#classLink",
                            "rdfsLabel": null
                        },
                        "origin": "TfIdfModel",
                        "confidenceScore": 0.041998205381678734
                    }
                ],
                "modelIds": null
            },
            {
                "id": "HN16832",
                "label": {
                    "uri": "HN16832",
                    "rdfsLabel": null
                },
                "type": "ColumnNode",
                "hNodeId": "HN16832",
                "columnName": "ProductionURI",
                "rdfLiteralType": null,
                "language": "",
                "userSemanticTypes": [
                    {
                        "hNodeId": "HN16832",
                        "domain": {
                            "uri": "http://www.cidoc-crm.org/cidoc-crm/E12_Production",
                            "rdfsLabel": null
                        },
                        "type": {
                            "uri": "http://isi.edu/integration/karma/dev#classLink",
                            "rdfsLabel": null
                        },
                        "origin": "User",
                        "confidenceScore": 1.0
                    }
                ],
                "learnedSemanticTypes": [
                    {
                        "hNodeId": "HN16832",
                        "domain": {
                            "uri": "http://www.cidoc-crm.org/cidoc-crm/E12_Production",
                            "rdfsLabel": null
                        },
                        "type": {
                            "uri": "http://isi.edu/integration/karma/dev#classLink",
                            "rdfsLabel": null
                        },
                        "origin": "TfIdfModel",
                        "confidenceScore": 0.5552889342379713
                    },
                    {
                        "hNodeId": "HN16832",
                        "domain": {
                            "uri": "http://www.cidoc-crm.org/cidoc-crm/E52_Time-Span",
                            "rdfsLabel": null
                        },
                        "type": {
                            "uri": "http://isi.edu/integration/karma/dev#classLink",
                            "rdfsLabel": null
                        },
                        "origin": "TfIdfModel",
                        "confidenceScore": 0.3031903964480099
                    },
                    {
                        "hNodeId": "HN16832",
                        "domain": {
                            "uri": "http://www.cidoc-crm.org/cidoc-crm/E22_Man-Made_Object",
                            "rdfsLabel": null
                        },
                        "type": {
                            "uri": "http://isi.edu/integration/karma/dev#classLink",
                            "rdfsLabel": null
                        },
                        "origin": "TfIdfModel",
                        "confidenceScore": 0.08281127708841594
                    },
                    {
                        "hNodeId": "HN16832",
                        "domain": {
                            "uri": "http://www.cidoc-crm.org/cidoc-crm/E33_Linguistic_Object",
                            "rdfsLabel": null
                        },
                        "type": {
                            "uri": "http://isi.edu/integration/karma/dev#classLink",
                            "rdfsLabel": null
                        },
                        "origin": "TfIdfModel",
                        "confidenceScore": 0.05870939222560282
                    }
                ],
                "modelIds": null
            },
            {
                "id": "HN17743",
                "label": {
                    "uri": "HN17743",
                    "rdfsLabel": null
                },
                "type": "ColumnNode",
                "hNodeId": "HN17743",
                "columnName": "PlaceURI",
                "rdfLiteralType": null,
                "language": "",
                "userSemanticTypes": [
                    {
                        "hNodeId": "HN17743",
                        "domain": {
                            "uri": "http://www.cidoc-crm.org/cidoc-crm/E53_Place",
                            "rdfsLabel": null
                        },
                        "type": {
                            "uri": "http://isi.edu/integration/karma/dev#classLink",
                            "rdfsLabel": null
                        },
                        "origin": "User",
                        "confidenceScore": 1.0
                    }
                ],
                "learnedSemanticTypes": [
                    {
                        "hNodeId": "HN17743",
                        "domain": {
                            "uri": "http://www.cidoc-crm.org/cidoc-crm/E12_Production",
                            "rdfsLabel": null
                        },
                        "type": {
                            "uri": "http://isi.edu/integration/karma/dev#classLink",
                            "rdfsLabel": null
                        },
                        "origin": "TfIdfModel",
                        "confidenceScore": 0.5651953500982929
                    },
                    {
                        "hNodeId": "HN17743",
                        "domain": {
                            "uri": "http://www.cidoc-crm.org/cidoc-crm/E52_Time-Span",
                            "rdfsLabel": null
                        },
                        "type": {
                            "uri": "http://isi.edu/integration/karma/dev#classLink",
                            "rdfsLabel": null
                        },
                        "origin": "TfIdfModel",
                        "confidenceScore": 0.28643286569012105
                    },
                    {
                        "hNodeId": "HN17743",
                        "domain": {
                            "uri": "http://www.cidoc-crm.org/cidoc-crm/E22_Man-Made_Object",
                            "rdfsLabel": null
                        },
                        "type": {
                            "uri": "http://isi.edu/integration/karma/dev#classLink",
                            "rdfsLabel": null
                        },
                        "origin": "TfIdfModel",
                        "confidenceScore": 0.08706353959558272
                    },
                    {
                        "hNodeId": "HN17743",
                        "domain": {
                            "uri": "http://www.cidoc-crm.org/cidoc-crm/E33_Linguistic_Object",
                            "rdfsLabel": null
                        },
                        "type": {
                            "uri": "http://isi.edu/integration/karma/dev#classLink",
                            "rdfsLabel": null
                        },
                        "origin": "TfIdfModel",
                        "confidenceScore": 0.061308244616003316
                    }
                ],
                "modelIds": null
            },
            {
                "id": "HN16017",
                "label": {
                    "uri": "HN16017",
                    "rdfsLabel": null
                },
                "type": "ColumnNode",
                "hNodeId": "HN16017",
                "columnName": "ObjectURI",
                "rdfLiteralType": null,
                "language": "",
                "userSemanticTypes": [
                    {
                        "hNodeId": "HN16017",
                        "domain": {
                            "uri": "http://www.cidoc-crm.org/cidoc-crm/E22_Man-Made_Object",
                            "rdfsLabel": null
                        },
                        "type": {
                            "uri": "http://isi.edu/integration/karma/dev#classLink",
                            "rdfsLabel": null
                        },
                        "origin": "User",
                        "confidenceScore": 1.0
                    }
                ],
                "learnedSemanticTypes": [
                    {
                        "hNodeId": "HN16017",
                        "domain": {
                            "uri": "http://www.cidoc-crm.org/cidoc-crm/E22_Man-Made_Object",
                            "rdfsLabel": null
                        },
                        "type": {
                            "uri": "http://isi.edu/integration/karma/dev#classLink",
                            "rdfsLabel": null
                        },
                        "origin": "TfIdfModel",
                        "confidenceScore": 0.34017723646325726
                    },
                    {
                        "hNodeId": "HN16017",
                        "domain": {
                            "uri": "http://www.cidoc-crm.org/cidoc-crm/E33_Linguistic_Object",
                            "rdfsLabel": null
                        },
                        "type": {
                            "uri": "http://isi.edu/integration/karma/dev#classLink",
                            "rdfsLabel": null
                        },
                        "origin": "TfIdfModel",
                        "confidenceScore": 0.2427851228484138
                    },
                    {
                        "hNodeId": "HN16017",
                        "domain": {
                            "uri": "http://www.cidoc-crm.org/cidoc-crm/E40_Legal_Body",
                            "rdfsLabel": null
                        },
                        "type": {
                            "uri": "http://isi.edu/integration/karma/dev#classLink",
                            "rdfsLabel": null
                        },
                        "origin": "TfIdfModel",
                        "confidenceScore": 0.21532595086339704
                    },
                    {
                        "hNodeId": "HN16017",
                        "domain": {
                            "uri": "http://www.cidoc-crm.org/cidoc-crm/E12_Production",
                            "rdfsLabel": null
                        },
                        "type": {
                            "uri": "http://isi.edu/integration/karma/dev#classLink",
                            "rdfsLabel": null
                        },
                        "origin": "TfIdfModel",
                        "confidenceScore": 0.2017116898249319
                    }
                ],
                "modelIds": null
            },
            {
                "id": "HN20461",
                "label": {
                    "uri": "HN20461",
                    "rdfsLabel": null
                },
                "type": "ColumnNode",
                "hNodeId": "HN20461",
                "columnName": "LongitudeURI",
                "rdfLiteralType": null,
                "language": "",
                "userSemanticTypes": [
                    {
                        "hNodeId": "HN20461",
                        "domain": {
                            "uri": "http://www.cidoc-crm.org/cidoc-crm/E47_Spatial_Coordinates",
                            "rdfsLabel": null
                        },
                        "type": {
                            "uri": "http://isi.edu/integration/karma/dev#classLink",
                            "rdfsLabel": null
                        },
                        "origin": "User",
                        "confidenceScore": 1.0
                    }
                ],
                "learnedSemanticTypes": [
                    {
                        "hNodeId": "HN20461",
                        "domain": {
                            "uri": "http://www.cidoc-crm.org/cidoc-crm/E53_Place",
                            "rdfsLabel": null
                        },
                        "type": {
                            "uri": "http://isi.edu/integration/karma/dev#classLink",
                            "rdfsLabel": null
                        },
                        "origin": "TfIdfModel",
                        "confidenceScore": 0.39357944793349875
                    },
                    {
                        "hNodeId": "HN20461",
                        "domain": {
                            "uri": "http://www.cidoc-crm.org/cidoc-crm/E47_Spatial_Coordinates",
                            "rdfsLabel": null
                        },
                        "type": {
                            "uri": "http://isi.edu/integration/karma/dev#classLink",
                            "rdfsLabel": null
                        },
                        "origin": "TfIdfModel",
                        "confidenceScore": 0.32566959370764365
                    },
                    {
                        "hNodeId": "HN20461",
                        "domain": {
                            "uri": "http://www.cidoc-crm.org/cidoc-crm/E12_Production",
                            "rdfsLabel": null
                        },
                        "type": {
                            "uri": "http://isi.edu/integration/karma/dev#classLink",
                            "rdfsLabel": null
                        },
                        "origin": "TfIdfModel",
                        "confidenceScore": 0.1842336486558758
                    },
                    {
                        "hNodeId": "HN20461",
                        "domain": {
                            "uri": "http://www.cidoc-crm.org/cidoc-crm/E52_Time-Span",
                            "rdfsLabel": null
                        },
                        "type": {
                            "uri": "http://isi.edu/integration/karma/dev#classLink",
                            "rdfsLabel": null
                        },
                        "origin": "TfIdfModel",
                        "confidenceScore": 0.09651730970298183
                    }
                ],
                "modelIds": null
            },
            {
                "id": "http://vocab.getty.edu/aat/3003875671",
                "label": {
                    "uri": "",
                    "rdfsLabel": null
                },
                "type": "LiteralNode",
                "value": "http://vocab.getty.edu/aat/300387567",
                "datatype": {
                    "uri": "",
                    "rdfsLabel": null
                },
                "language": "",
                "isUri": "true",
                "modelIds": null
            },
            {
                "id": "http://vocab.getty.edu/aat/3003875651",
                "label": {
                    "uri": "",
                    "rdfsLabel": null
                },
                "type": "LiteralNode",
                "value": "http://vocab.getty.edu/aat/300387565",
                "datatype": {
                    "uri": "",
                    "rdfsLabel": null
                },
                "language": "",
                "isUri": "true",
                "modelIds": null
            }
        ],
        "links": [
            {
                "id": "http://www.cidoc-crm.org/cidoc-crm/E12_Production1---http://www.cidoc-crm.org/cidoc-crm/P7_took_place_at---http://www.cidoc-crm.org/cidoc-crm/E53_Place1",
                "weight": 0.009999999776482582,
                "type": "ObjectPropertyLink",
                "label": {
                    "uri": "http://www.cidoc-crm.org/cidoc-crm/P7_took_place_at",
                    "rdfsLabel": null
                },
                "objectPropertyType": "Indirect",
                "status": "ForcedByUser",
                "keyInfo": "None",
                "modelIds": null
            },
            {
                "id": "http://www.cidoc-crm.org/cidoc-crm/E22_Man-Made_Object1---http://www.cidoc-crm.org/cidoc-crm/P108i_was_produced_by---http://www.cidoc-crm.org/cidoc-crm/E12_Production1",
                "weight": 0.009999999776482582,
                "type": "ObjectPropertyLink",
                "label": {
                    "uri": "http://www.cidoc-crm.org/cidoc-crm/P108i_was_produced_by",
                    "rdfsLabel": null
                },
                "objectPropertyType": "Indirect",
                "status": "ForcedByUser",
                "keyInfo": "None",
                "modelIds": null
            },
            {
                "id": "http://www.cidoc-crm.org/cidoc-crm/E53_Place1---http://www.cidoc-crm.org/cidoc-crm/P87_is_identified_by---http://www.cidoc-crm.org/cidoc-crm/E47_Spatial_Coordinates1",
                "weight": 0.009999999776482582,
                "type": "ObjectPropertyLink",
                "label": {
                    "uri": "http://www.cidoc-crm.org/cidoc-crm/P87_is_identified_by",
                    "rdfsLabel": null
                },
                "objectPropertyType": "Indirect",
                "status": "ForcedByUser",
                "keyInfo": "None",
                "modelIds": null
            },
            {
                "id": "http://www.cidoc-crm.org/cidoc-crm/E53_Place1---http://www.cidoc-crm.org/cidoc-crm/P87_is_identified_by---http://www.cidoc-crm.org/cidoc-crm/E47_Spatial_Coordinates2",
                "weight": 0.009999999776482582,
                "type": "ObjectPropertyLink",
                "label": {
                    "uri": "http://www.cidoc-crm.org/cidoc-crm/P87_is_identified_by",
                    "rdfsLabel": null
                },
                "objectPropertyType": "Indirect",
                "status": "ForcedByUser",
                "keyInfo": "None",
                "modelIds": null
            },
            {
                "id": "http://www.cidoc-crm.org/cidoc-crm/E47_Spatial_Coordinates1---http://www.w3.org/1999/02/22-rdf-syntax-ns#value---HN19564",
                "weight": 0.01,
                "type": "DataPropertyLink",
                "label": {
                    "uri": "http://www.w3.org/1999/02/22-rdf-syntax-ns#value",
                    "rdfsLabel": null
                },
                "status": "ForcedByUser",
                "keyInfo": "None",
                "modelIds": null
            },
            {
                "id": "http://www.cidoc-crm.org/cidoc-crm/E47_Spatial_Coordinates2---http://www.w3.org/1999/02/22-rdf-syntax-ns#value---HN21359",
                "weight": 0.01,
                "type": "DataPropertyLink",
                "label": {
                    "uri": "http://www.w3.org/1999/02/22-rdf-syntax-ns#value",
                    "rdfsLabel": null
                },
                "status": "ForcedByUser",
                "keyInfo": "None",
                "modelIds": null
            },
            {
                "id": "http://www.cidoc-crm.org/cidoc-crm/E53_Place1---http://www.w3.org/2000/01/rdf-schema#label---HN37",
                "weight": 0.01,
                "type": "DataPropertyLink",
                "label": {
                    "uri": "http://www.w3.org/2000/01/rdf-schema#label",
                    "rdfsLabel": null
                },
                "status": "ForcedByUser",
                "keyInfo": "None",
                "modelIds": null
            },
            {
                "id": "http://www.cidoc-crm.org/cidoc-crm/E47_Spatial_Coordinates1---http://isi.edu/integration/karma/dev#classLink---HN18664",
                "weight": 0.01,
                "type": "ClassInstanceLink",
                "label": {
                    "uri": "http://isi.edu/integration/karma/dev#classLink",
                    "rdfsLabel": null
                },
                "status": "ForcedByUser",
                "keyInfo": "UriOfInstance",
                "modelIds": null
            },
            {
                "id": "http://www.cidoc-crm.org/cidoc-crm/E12_Production1---http://isi.edu/integration/karma/dev#classLink---HN16832",
                "weight": 0.01,
                "type": "ClassInstanceLink",
                "label": {
                    "uri": "http://isi.edu/integration/karma/dev#classLink",
                    "rdfsLabel": null
                },
                "status": "ForcedByUser",
                "keyInfo": "UriOfInstance",
                "modelIds": null
            },
            {
                "id": "http://www.cidoc-crm.org/cidoc-crm/E53_Place1---http://isi.edu/integration/karma/dev#classLink---HN17743",
                "weight": 0.01,
                "type": "ClassInstanceLink",
                "label": {
                    "uri": "http://isi.edu/integration/karma/dev#classLink",
                    "rdfsLabel": null
                },
                "status": "ForcedByUser",
                "keyInfo": "UriOfInstance",
                "modelIds": null
            },
            {
                "id": "http://www.cidoc-crm.org/cidoc-crm/E22_Man-Made_Object1---http://isi.edu/integration/karma/dev#classLink---HN16017",
                "weight": 0.01,
                "type": "ClassInstanceLink",
                "label": {
                    "uri": "http://isi.edu/integration/karma/dev#classLink",
                    "rdfsLabel": null
                },
                "status": "ForcedByUser",
                "keyInfo": "UriOfInstance",
                "modelIds": null
            },
            {
                "id": "http://www.cidoc-crm.org/cidoc-crm/E47_Spatial_Coordinates2---http://isi.edu/integration/karma/dev#classLink---HN20461",
                "weight": 0.01,
                "type": "ClassInstanceLink",
                "label": {
                    "uri": "http://isi.edu/integration/karma/dev#classLink",
                    "rdfsLabel": null
                },
                "status": "ForcedByUser",
                "keyInfo": "UriOfInstance",
                "modelIds": null
            },
            {
                "id": "http://www.cidoc-crm.org/cidoc-crm/E47_Spatial_Coordinates2---http://www.cidoc-crm.org/cidoc-crm/P2_has_type---http://vocab.getty.edu/aat/3003875671",
                "weight": 0.01,
                "type": "ObjectPropertyLink",
                "label": {
                    "uri": "http://www.cidoc-crm.org/cidoc-crm/P2_has_type",
                    "rdfsLabel": "has type"
                },
                "objectPropertyType": "None",
                "status": "ForcedByUser",
                "keyInfo": "None",
                "modelIds": null
            },
            {
                "id": "http://www.cidoc-crm.org/cidoc-crm/E47_Spatial_Coordinates1---http://www.cidoc-crm.org/cidoc-crm/P2_has_type---http://vocab.getty.edu/aat/3003875651",
                "weight": 0.01,
                "type": "ObjectPropertyLink",
                "label": {
                    "uri": "http://www.cidoc-crm.org/cidoc-crm/P2_has_type",
                    "rdfsLabel": "has type"
                },
                "objectPropertyType": "None",
                "status": "ForcedByUser",
                "keyInfo": "None",
                "modelIds": null
            }
        ]
    }
}